{
"meta":{"test_sets":[],"test_metrics":[],"learn_metrics":[{"best_value":"Min","name":"RMSE"}],"launch_mode":"Train","parameters":"","iteration_count":1000,"learn_sets":["learn"],"name":"experiment"},
"iterations":[
{"learn":[7580.542224],"iteration":0,"passed_time":0.1752407168,"remaining_time":175.065476},
{"learn":[7429.926986],"iteration":1,"passed_time":0.1787529083,"remaining_time":89.19770123},
{"learn":[7296.805519],"iteration":2,"passed_time":0.1816506218,"remaining_time":60.36855664},
{"learn":[7147.937928],"iteration":3,"passed_time":0.184685965,"remaining_time":45.98680528},
{"learn":[7008.733024],"iteration":4,"passed_time":0.188020973,"remaining_time":37.41617364},
{"learn":[6883.332838],"iteration":5,"passed_time":0.1911416652,"remaining_time":31.66580253},
{"learn":[6765.144971],"iteration":6,"passed_time":0.1939284773,"remaining_time":27.51013971},
{"learn":[6657.228883],"iteration":7,"passed_time":0.1970943982,"remaining_time":24.43970538},
{"learn":[6527.897432],"iteration":8,"passed_time":0.1999078845,"remaining_time":22.01207928},
{"learn":[6405.74319],"iteration":9,"passed_time":0.2026022311,"remaining_time":20.05762088},
{"learn":[6301.65802],"iteration":10,"passed_time":0.2054787515,"remaining_time":18.47440775},
{"learn":[6174.37587],"iteration":11,"passed_time":0.2083043118,"remaining_time":17.15038834},
{"learn":[6066.772061],"iteration":12,"passed_time":0.2115416713,"remaining_time":16.06089459},
{"learn":[5951.353483],"iteration":13,"passed_time":0.2142086666,"remaining_time":15.08641038},
{"learn":[5842.114902],"iteration":14,"passed_time":0.2169172997,"remaining_time":14.24423601},
{"learn":[5732.732915],"iteration":15,"passed_time":0.21958068,"remaining_time":13.50421182},
{"learn":[5641.564935],"iteration":16,"passed_time":0.22226202,"remaining_time":12.85197445},
{"learn":[5537.37745],"iteration":17,"passed_time":0.224983771,"remaining_time":12.27411462},
{"learn":[5432.787353],"iteration":18,"passed_time":0.2277280028,"remaining_time":11.75795635},
{"learn":[5350.082588],"iteration":19,"passed_time":0.2290797398,"remaining_time":11.22490725},
{"learn":[5262.594407],"iteration":20,"passed_time":0.2317782918,"remaining_time":10.80528322},
{"learn":[5180.320482],"iteration":21,"passed_time":0.2346548176,"remaining_time":10.43147325},
{"learn":[5087.315612],"iteration":22,"passed_time":0.2373450867,"remaining_time":10.08200651},
{"learn":[5014.557654],"iteration":23,"passed_time":0.2400217112,"remaining_time":9.760882922},
{"learn":[4930.616641],"iteration":24,"passed_time":0.2427120606,"remaining_time":9.465770364},
{"learn":[4854.131331],"iteration":25,"passed_time":0.2454482487,"remaining_time":9.194869008},
{"learn":[4775.750607],"iteration":26,"passed_time":0.2481228607,"remaining_time":8.941612719},
{"learn":[4708.175848],"iteration":27,"passed_time":0.2511030198,"remaining_time":8.716861974},
{"learn":[4628.69329],"iteration":28,"passed_time":0.2541496741,"remaining_time":8.509632193},
{"learn":[4550.737301],"iteration":29,"passed_time":0.2569639717,"remaining_time":8.308501753},
{"learn":[4475.894262],"iteration":30,"passed_time":0.2597749966,"remaining_time":8.120063603},
{"learn":[4408.203827],"iteration":31,"passed_time":0.2627901711,"remaining_time":7.949402675},
{"learn":[4349.282648],"iteration":32,"passed_time":0.2657722674,"remaining_time":7.787932806},
{"learn":[4284.004518],"iteration":33,"passed_time":0.2674035548,"remaining_time":7.59740688},
{"learn":[4226.809114],"iteration":34,"passed_time":0.2700267789,"remaining_time":7.445024047},
{"learn":[4163.135904],"iteration":35,"passed_time":0.2727419352,"remaining_time":7.303422931},
{"learn":[4099.125355],"iteration":36,"passed_time":0.2755204131,"remaining_time":7.170977239},
{"learn":[4042.019244],"iteration":37,"passed_time":0.2781343332,"remaining_time":7.041190226},
{"learn":[3998.082543],"iteration":38,"passed_time":0.2806208152,"remaining_time":6.914784702},
{"learn":[3933.50595],"iteration":39,"passed_time":0.2834385589,"remaining_time":6.802525414},
{"learn":[3882.044762],"iteration":40,"passed_time":0.2862892451,"remaining_time":6.696375269},
{"learn":[3829.154211],"iteration":41,"passed_time":0.2881255845,"remaining_time":6.57200738},
{"learn":[3768.773818],"iteration":42,"passed_time":0.2910274769,"remaining_time":6.477053382},
{"learn":[3710.833461],"iteration":43,"passed_time":0.2938473982,"remaining_time":6.384502561},
{"learn":[3660.759801],"iteration":44,"passed_time":0.2964332371,"remaining_time":6.290972031},
{"learn":[3607.557833],"iteration":45,"passed_time":0.2991826536,"remaining_time":6.204788076},
{"learn":[3551.436393],"iteration":46,"passed_time":0.3018969029,"remaining_time":6.121441456},
{"learn":[3506.929293],"iteration":47,"passed_time":0.3043960344,"remaining_time":6.037188016},
{"learn":[3460.888561],"iteration":48,"passed_time":0.3071784761,"remaining_time":5.961770016},
{"learn":[3424.748739],"iteration":49,"passed_time":0.3098482857,"remaining_time":5.887117428},
{"learn":[3381.161741],"iteration":50,"passed_time":0.3124186453,"remaining_time":5.813437145},
{"learn":[3341.232364],"iteration":51,"passed_time":0.3148635403,"remaining_time":5.740204542},
{"learn":[3297.082682],"iteration":52,"passed_time":0.3177721048,"remaining_time":5.677927986},
{"learn":[3257.913115],"iteration":53,"passed_time":0.3205149663,"remaining_time":5.614947372},
{"learn":[3207.146513],"iteration":54,"passed_time":0.3218124266,"remaining_time":5.529322603},
{"learn":[3166.290625],"iteration":55,"passed_time":0.3245949366,"remaining_time":5.471743216},
{"learn":[3116.043378],"iteration":56,"passed_time":0.3274202979,"remaining_time":5.416795454},
{"learn":[3075.357175],"iteration":57,"passed_time":0.3300088447,"remaining_time":5.359798822},
{"learn":[3042.032051],"iteration":58,"passed_time":0.3324404318,"remaining_time":5.302143158},
{"learn":[3004.477395],"iteration":59,"passed_time":0.3349305895,"remaining_time":5.247245902},
{"learn":[2970.432676],"iteration":60,"passed_time":0.337506056,"remaining_time":5.195380109},
{"learn":[2933.876526],"iteration":61,"passed_time":0.3403126268,"remaining_time":5.148600709},
{"learn":[2898.628535],"iteration":62,"passed_time":0.34318609,"remaining_time":5.104212164},
{"learn":[2870.065482],"iteration":63,"passed_time":0.3460762331,"remaining_time":5.061364909},
{"learn":[2834.704519],"iteration":64,"passed_time":0.3488349942,"remaining_time":5.017857224},
{"learn":[2800.303284],"iteration":65,"passed_time":0.3518000283,"remaining_time":4.97850343},
{"learn":[2771.216038],"iteration":66,"passed_time":0.354609581,"remaining_time":4.938070732},
{"learn":[2737.357303],"iteration":67,"passed_time":0.357017372,"remaining_time":4.893238099},
{"learn":[2716.347314],"iteration":68,"passed_time":0.3598986112,"remaining_time":4.85602329},
{"learn":[2685.336535],"iteration":69,"passed_time":0.3623341803,"remaining_time":4.813868395},
{"learn":[2664.260052],"iteration":70,"passed_time":0.3663456107,"remaining_time":4.793451723},
{"learn":[2633.387747],"iteration":71,"passed_time":0.3694372778,"remaining_time":4.761636024},
{"learn":[2602.571802],"iteration":72,"passed_time":0.3717859459,"remaining_time":4.721172217},
{"learn":[2576.564537],"iteration":73,"passed_time":0.3744352007,"remaining_time":4.685499945},
{"learn":[2551.729821],"iteration":74,"passed_time":0.3768730136,"remaining_time":4.648100501},
{"learn":[2526.590974],"iteration":75,"passed_time":0.3790714583,"remaining_time":4.608710888},
{"learn":[2503.775027],"iteration":76,"passed_time":0.381408416,"remaining_time":4.571947636},
{"learn":[2478.927079],"iteration":77,"passed_time":0.3839122263,"remaining_time":4.538039393},
{"learn":[2458.721061],"iteration":78,"passed_time":0.3852843902,"remaining_time":4.491733207},
{"learn":[2435.880435],"iteration":79,"passed_time":0.3867807563,"remaining_time":4.447978697},
{"learn":[2411.010096],"iteration":80,"passed_time":0.3893530613,"remaining_time":4.417474856},
{"learn":[2388.214372],"iteration":81,"passed_time":0.3909697094,"remaining_time":4.376953576},
{"learn":[2368.334583],"iteration":82,"passed_time":0.3936557934,"remaining_time":4.349185091},
{"learn":[2347.068508],"iteration":83,"passed_time":0.3965054696,"remaining_time":4.32379774},
{"learn":[2326.813163],"iteration":84,"passed_time":0.3993836529,"remaining_time":4.299247557},
{"learn":[2306.238418],"iteration":85,"passed_time":0.4018016263,"remaining_time":4.270310308},
{"learn":[2283.267697],"iteration":86,"passed_time":0.4045905143,"remaining_time":4.245875167},
{"learn":[2268.544952],"iteration":87,"passed_time":0.4065476582,"remaining_time":4.213312094},
{"learn":[2250.024926],"iteration":88,"passed_time":0.4085330303,"remaining_time":4.181725737},
{"learn":[2238.308192],"iteration":89,"passed_time":0.411288706,"remaining_time":4.158585805},
{"learn":[2218.531619],"iteration":90,"passed_time":0.4142246518,"remaining_time":4.137694598},
{"learn":[2196.750885],"iteration":91,"passed_time":0.4167117779,"remaining_time":4.112764069},
{"learn":[2178.799185],"iteration":92,"passed_time":0.4195465442,"remaining_time":4.091706619},
{"learn":[2164.00587],"iteration":93,"passed_time":0.4224014051,"remaining_time":4.071230564},
{"learn":[2146.7765],"iteration":94,"passed_time":0.4251442036,"remaining_time":4.05005794},
{"learn":[2131.01967],"iteration":95,"passed_time":0.4280351507,"remaining_time":4.030664335},
{"learn":[2116.30339],"iteration":96,"passed_time":0.4294774238,"remaining_time":3.998124884},
{"learn":[2105.079117],"iteration":97,"passed_time":0.431999022,"remaining_time":3.976154264},
{"learn":[2091.986136],"iteration":98,"passed_time":0.4346627052,"remaining_time":3.955869671},
{"learn":[2083.938712],"iteration":99,"passed_time":0.4373082495,"remaining_time":3.935774246},
{"learn":[2069.528746],"iteration":100,"passed_time":0.4399369298,"remaining_time":3.915874256},
{"learn":[2057.132484],"iteration":101,"passed_time":0.4423786199,"remaining_time":3.894666673},
{"learn":[2045.870496],"iteration":102,"passed_time":0.4451074159,"remaining_time":3.876323806},
{"learn":[2030.917791],"iteration":103,"passed_time":0.4479353842,"remaining_time":3.859135618},
{"learn":[2021.004401],"iteration":104,"passed_time":0.4507454885,"remaining_time":3.842068687},
{"learn":[2006.148121],"iteration":105,"passed_time":0.453534654,"remaining_time":3.825094157},
{"learn":[1990.067225],"iteration":106,"passed_time":0.4562553123,"remaining_time":3.807813027},
{"learn":[1976.179524],"iteration":107,"passed_time":0.4591228262,"remaining_time":3.792014453},
{"learn":[1958.87675],"iteration":108,"passed_time":0.4617873215,"remaining_time":3.77479361},
{"learn":[1947.391169],"iteration":109,"passed_time":0.4646622725,"remaining_time":3.759540205},
{"learn":[1938.129273],"iteration":110,"passed_time":0.4665088668,"remaining_time":3.736273717},
{"learn":[1924.552605],"iteration":111,"passed_time":0.4692122237,"remaining_time":3.720182631},
{"learn":[1914.845199],"iteration":112,"passed_time":0.4720802121,"remaining_time":3.70562078},
{"learn":[1904.057144],"iteration":113,"passed_time":0.475217254,"remaining_time":3.69335515},
{"learn":[1890.206587],"iteration":114,"passed_time":0.4780762322,"remaining_time":3.679108395},
{"learn":[1877.889642],"iteration":115,"passed_time":0.4809438743,"remaining_time":3.665124007},
{"learn":[1867.373047],"iteration":116,"passed_time":0.4832504759,"remaining_time":3.647095472},
{"learn":[1859.100184],"iteration":117,"passed_time":0.485014615,"remaining_time":3.625278732},
{"learn":[1849.652764],"iteration":118,"passed_time":0.4867100147,"remaining_time":3.603290109},
{"learn":[1841.241533],"iteration":119,"passed_time":0.4890184158,"remaining_time":3.586135049},
{"learn":[1831.162389],"iteration":120,"passed_time":0.4912966557,"remaining_time":3.569006284},
{"learn":[1825.447055],"iteration":121,"passed_time":0.4930536046,"remaining_time":3.548369384},
{"learn":[1818.998996],"iteration":122,"passed_time":0.4945583243,"remaining_time":3.526241061},
{"learn":[1809.419223],"iteration":123,"passed_time":0.496747614,"remaining_time":3.509281531},
{"learn":[1796.839433],"iteration":124,"passed_time":0.4985897881,"remaining_time":3.490128517},
{"learn":[1789.370367],"iteration":125,"passed_time":0.5007887045,"remaining_time":3.473724823},
{"learn":[1782.765021],"iteration":126,"passed_time":0.503524967,"remaining_time":3.461238553},
{"learn":[1774.893163],"iteration":127,"passed_time":0.5059249734,"remaining_time":3.446613881},
{"learn":[1766.627513],"iteration":128,"passed_time":0.5086909647,"remaining_time":3.434649847},
{"learn":[1755.346741],"iteration":129,"passed_time":0.5116836312,"remaining_time":3.424344301},
{"learn":[1743.65537],"iteration":130,"passed_time":0.5145987859,"remaining_time":3.413636221},
{"learn":[1733.117953],"iteration":131,"passed_time":0.5170135479,"remaining_time":3.399755754},
{"learn":[1727.813922],"iteration":132,"passed_time":0.5190262921,"remaining_time":3.383427032},
{"learn":[1719.617849],"iteration":133,"passed_time":0.5217620151,"remaining_time":3.371984366},
{"learn":[1710.665902],"iteration":134,"passed_time":0.5243921,"remaining_time":3.359993826},
{"learn":[1701.144793],"iteration":135,"passed_time":0.5267048504,"remaining_time":3.346124932},
{"learn":[1693.324736],"iteration":136,"passed_time":0.529447896,"remaining_time":3.335135287},
{"learn":[1688.543811],"iteration":137,"passed_time":0.5316670523,"remaining_time":3.320992747},
{"learn":[1679.304839],"iteration":138,"passed_time":0.5343654677,"remaining_time":3.309990415},
{"learn":[1672.416113],"iteration":139,"passed_time":0.5366348161,"remaining_time":3.296471013},
{"learn":[1665.719252],"iteration":140,"passed_time":0.5390033939,"remaining_time":3.283715712},
{"learn":[1656.403315],"iteration":141,"passed_time":0.541184392,"remaining_time":3.269973298},
{"learn":[1648.184878],"iteration":142,"passed_time":0.5430368793,"remaining_time":3.254423815},
{"learn":[1638.381358],"iteration":143,"passed_time":0.5454143309,"remaining_time":3.242185189},
{"learn":[1630.708296],"iteration":144,"passed_time":0.5481331186,"remaining_time":3.232095286},
{"learn":[1623.020959],"iteration":145,"passed_time":0.5511098362,"remaining_time":3.223615069},
{"learn":[1616.906721],"iteration":146,"passed_time":0.5538107805,"remaining_time":3.213609495},
{"learn":[1608.977444],"iteration":147,"passed_time":0.5567182416,"remaining_time":3.204891499},
{"learn":[1604.056165],"iteration":148,"passed_time":0.5590248971,"remaining_time":3.19282005},
{"learn":[1600.209474],"iteration":149,"passed_time":0.5627031525,"remaining_time":3.188651197},
{"learn":[1594.439067],"iteration":150,"passed_time":0.5655283152,"remaining_time":3.179692315},
{"learn":[1588.134253],"iteration":151,"passed_time":0.5677780286,"remaining_time":3.167603738},
{"learn":[1578.053449],"iteration":152,"passed_time":0.5704578575,"remaining_time":3.158024871},
{"learn":[1572.678694],"iteration":153,"passed_time":0.5723104495,"remaining_time":3.143991171},
{"learn":[1568.668127],"iteration":154,"passed_time":0.5746766036,"remaining_time":3.132914387},
{"learn":[1563.320231],"iteration":155,"passed_time":0.5769940724,"remaining_time":3.121685879},
{"learn":[1558.193022],"iteration":156,"passed_time":0.5793590424,"remaining_time":3.110825941},
{"learn":[1550.809376],"iteration":157,"passed_time":0.5811057803,"remaining_time":3.096778905},
{"learn":[1546.523263],"iteration":158,"passed_time":0.5833018091,"remaining_time":3.085263028},
{"learn":[1541.467421],"iteration":159,"passed_time":0.5851935068,"remaining_time":3.072265911},
{"learn":[1536.170692],"iteration":160,"passed_time":0.5870332638,"remaining_time":3.059136076},
{"learn":[1529.844368],"iteration":161,"passed_time":0.5894876709,"remaining_time":3.049325113},
{"learn":[1522.942764],"iteration":162,"passed_time":0.5922567418,"remaining_time":3.041220202},
{"learn":[1514.97469],"iteration":163,"passed_time":0.5945524056,"remaining_time":3.030767141},
{"learn":[1512.522513],"iteration":164,"passed_time":0.5971948311,"remaining_time":3.022167781},
{"learn":[1509.446586],"iteration":165,"passed_time":0.5986317143,"remaining_time":3.007583432},
{"learn":[1505.637268],"iteration":166,"passed_time":0.6006952977,"remaining_time":2.996282533},
{"learn":[1495.969657],"iteration":167,"passed_time":0.6028705215,"remaining_time":2.985644487},
{"learn":[1488.642217],"iteration":168,"passed_time":0.6054776056,"remaining_time":2.97723012},
{"learn":[1484.796279],"iteration":169,"passed_time":0.6079122234,"remaining_time":2.968042032},
{"learn":[1477.120252],"iteration":170,"passed_time":0.6108062194,"remaining_time":2.961159976},
{"learn":[1474.029393],"iteration":171,"passed_time":0.6135823195,"remaining_time":2.953756747},
{"learn":[1469.659086],"iteration":172,"passed_time":0.6158040166,"remaining_time":2.943756773},
{"learn":[1463.509815],"iteration":173,"passed_time":0.6175238521,"remaining_time":2.931463803},
{"learn":[1459.961788],"iteration":174,"passed_time":0.6200533575,"remaining_time":2.923108685},
{"learn":[1452.8421],"iteration":175,"passed_time":0.6226313189,"remaining_time":2.915046629},
{"learn":[1447.903606],"iteration":176,"passed_time":0.6249125746,"remaining_time":2.905666943},
{"learn":[1443.239666],"iteration":177,"passed_time":0.6279939385,"remaining_time":2.900061896},
{"learn":[1438.385395],"iteration":178,"passed_time":0.6309921289,"remaining_time":2.894103563},
{"learn":[1431.986585],"iteration":179,"passed_time":0.6333524367,"remaining_time":2.885272212},
{"learn":[1427.212454],"iteration":180,"passed_time":0.6359436609,"remaining_time":2.877557228},
{"learn":[1422.690755],"iteration":181,"passed_time":0.6385985225,"remaining_time":2.870184568},
{"learn":[1419.103265],"iteration":182,"passed_time":0.6417481656,"remaining_time":2.865072412},
{"learn":[1416.381173],"iteration":183,"passed_time":0.6445529101,"remaining_time":2.858452036},
{"learn":[1411.334255],"iteration":184,"passed_time":0.6472210759,"remaining_time":2.851271226},
{"learn":[1407.794115],"iteration":185,"passed_time":0.6496765993,"remaining_time":2.843208343},
{"learn":[1404.691524],"iteration":186,"passed_time":0.6521223851,"remaining_time":2.835163097},
{"learn":[1399.344313],"iteration":187,"passed_time":0.653992288,"remaining_time":2.824690095},
{"learn":[1394.24525],"iteration":188,"passed_time":0.6568738682,"remaining_time":2.818649244},
{"learn":[1392.678012],"iteration":189,"passed_time":0.6593041909,"remaining_time":2.810717866},
{"learn":[1387.297948],"iteration":190,"passed_time":0.662106445,"remaining_time":2.804419445},
{"learn":[1381.000873],"iteration":191,"passed_time":0.6646762204,"remaining_time":2.797179094},
{"learn":[1377.522738],"iteration":192,"passed_time":0.6671632646,"remaining_time":2.789641215},
{"learn":[1373.909191],"iteration":193,"passed_time":0.669586091,"remaining_time":2.781888605},
{"learn":[1367.690197],"iteration":194,"passed_time":0.6723979284,"remaining_time":2.775796576},
{"learn":[1364.551844],"iteration":195,"passed_time":0.6751663141,"remaining_time":2.769559778},
{"learn":[1363.11341],"iteration":196,"passed_time":0.6765583389,"remaining_time":2.75774795},
{"learn":[1356.292418],"iteration":197,"passed_time":0.679402283,"remaining_time":2.751922379},
{"learn":[1354.159208],"iteration":198,"passed_time":0.6815996557,"remaining_time":2.743524242},
{"learn":[1349.611218],"iteration":199,"passed_time":0.6842426815,"remaining_time":2.736970726},
{"learn":[1345.066271],"iteration":200,"passed_time":0.6876564785,"remaining_time":2.733520031},
{"learn":[1339.658631],"iteration":201,"passed_time":0.6902813485,"remaining_time":2.72695305},
{"learn":[1335.20331],"iteration":202,"passed_time":0.6927677291,"remaining_time":2.719881183},
{"learn":[1332.852756],"iteration":203,"passed_time":0.6952733752,"remaining_time":2.712929444},
{"learn":[1327.587564],"iteration":204,"passed_time":0.6973791272,"remaining_time":2.704470274},
{"learn":[1322.786495],"iteration":205,"passed_time":0.698651158,"remaining_time":2.692859318},
{"learn":[1320.892131],"iteration":206,"passed_time":0.7010257468,"remaining_time":2.685572064},
{"learn":[1319.625134],"iteration":207,"passed_time":0.7024546219,"remaining_time":2.67473106},
{"learn":[1317.209311],"iteration":208,"passed_time":0.7040725344,"remaining_time":2.664695573},
{"learn":[1315.24674],"iteration":209,"passed_time":0.7062072701,"remaining_time":2.656684492},
{"learn":[1310.328989],"iteration":210,"passed_time":0.7082200371,"remaining_time":2.64827303},
{"learn":[1304.249582],"iteration":211,"passed_time":0.7101396724,"remaining_time":2.639575764},
{"learn":[1299.794967],"iteration":212,"passed_time":0.712625024,"remaining_time":2.633032366},
{"learn":[1295.467485],"iteration":213,"passed_time":0.7146615038,"remaining_time":2.624878234},
{"learn":[1291.169823],"iteration":214,"passed_time":0.7176590372,"remaining_time":2.620289973},
{"learn":[1285.528688],"iteration":215,"passed_time":0.7203688983,"remaining_time":2.614672298},
{"learn":[1282.965453],"iteration":216,"passed_time":0.7223345502,"remaining_time":2.606396096},
{"learn":[1280.905855],"iteration":217,"passed_time":0.7250132012,"remaining_time":2.600735428},
{"learn":[1278.309406],"iteration":218,"passed_time":0.7275700746,"remaining_time":2.594667709},
{"learn":[1274.459133],"iteration":219,"passed_time":0.7301280122,"remaining_time":2.58863568},
{"learn":[1272.839388],"iteration":220,"passed_time":0.7333129826,"remaining_time":2.58484531},
{"learn":[1269.325878],"iteration":221,"passed_time":0.7363013547,"remaining_time":2.580371414},
{"learn":[1267.591491],"iteration":222,"passed_time":0.73897786,"remaining_time":2.574824203},
{"learn":[1262.703725],"iteration":223,"passed_time":0.7412387555,"remaining_time":2.567862831},
{"learn":[1259.077162],"iteration":224,"passed_time":0.7440826284,"remaining_time":2.562951276},
{"learn":[1257.542618],"iteration":225,"passed_time":0.7468632185,"remaining_time":2.557841288},
{"learn":[1254.289424],"iteration":226,"passed_time":0.7502290527,"remaining_time":2.554744748},
{"learn":[1249.507015],"iteration":227,"passed_time":0.7522619941,"remaining_time":2.547132717},
{"learn":[1247.61054],"iteration":228,"passed_time":0.7536965115,"remaining_time":2.537554631},
{"learn":[1245.834056],"iteration":229,"passed_time":0.7563325996,"remaining_time":2.532070007},
{"learn":[1242.061126],"iteration":230,"passed_time":0.7583790616,"remaining_time":2.524647179},
{"learn":[1240.241],"iteration":231,"passed_time":0.7611848698,"remaining_time":2.519784397},
{"learn":[1236.360804],"iteration":232,"passed_time":0.7640933169,"remaining_time":2.515277142},
{"learn":[1234.13787],"iteration":233,"passed_time":0.7663624489,"remaining_time":2.508690751},
{"learn":[1232.406492],"iteration":234,"passed_time":0.7680448812,"remaining_time":2.500231209},
{"learn":[1225.73035],"iteration":235,"passed_time":0.7699436234,"remaining_time":2.492529357},
{"learn":[1223.904178],"iteration":236,"passed_time":0.7727357837,"remaining_time":2.487752755},
{"learn":[1218.398228],"iteration":237,"passed_time":0.7751099773,"remaining_time":2.481654633},
{"learn":[1215.885242],"iteration":238,"passed_time":0.7777936327,"remaining_time":2.476573031},
{"learn":[1214.781805],"iteration":239,"passed_time":0.7803753096,"remaining_time":2.47118848},
{"learn":[1210.256346],"iteration":240,"passed_time":0.7831418542,"remaining_time":2.466409408},
{"learn":[1209.239311],"iteration":241,"passed_time":0.7847859409,"remaining_time":2.45813117},
{"learn":[1204.233376],"iteration":242,"passed_time":0.787089463,"remaining_time":2.451961825},
{"learn":[1202.205293],"iteration":243,"passed_time":0.7898232385,"remaining_time":2.447157247},
{"learn":[1200.821985],"iteration":244,"passed_time":0.7923350412,"remaining_time":2.441685535},
{"learn":[1197.959202],"iteration":245,"passed_time":0.7948696283,"remaining_time":2.436307722},
{"learn":[1194.839223],"iteration":246,"passed_time":0.7975659237,"remaining_time":2.431445913},
{"learn":[1191.72251],"iteration":247,"passed_time":0.8002458268,"remaining_time":2.426551862},
{"learn":[1189.902014],"iteration":248,"passed_time":0.8018633019,"remaining_time":2.418471244},
{"learn":[1188.40309],"iteration":249,"passed_time":0.804625814,"remaining_time":2.413877442},
{"learn":[1185.617237],"iteration":250,"passed_time":0.8070291693,"remaining_time":2.408226485},
{"learn":[1184.157593],"iteration":251,"passed_time":0.8096456137,"remaining_time":2.403233806},
{"learn":[1182.792902],"iteration":252,"passed_time":0.8123838713,"remaining_time":2.398619573},
{"learn":[1181.985763],"iteration":253,"passed_time":0.814930475,"remaining_time":2.393457222},
{"learn":[1180.836569],"iteration":254,"passed_time":0.8170713044,"remaining_time":2.387129889},
{"learn":[1179.578943],"iteration":255,"passed_time":0.8198563259,"remaining_time":2.382707447},
{"learn":[1177.910679],"iteration":256,"passed_time":0.8226594083,"remaining_time":2.378349963},
{"learn":[1177.103193],"iteration":257,"passed_time":0.8251807852,"remaining_time":2.373194351},
{"learn":[1176.041813],"iteration":258,"passed_time":0.8281209769,"remaining_time":2.369257312},
{"learn":[1174.435339],"iteration":259,"passed_time":0.8299647907,"remaining_time":2.362207481},
{"learn":[1169.505395],"iteration":260,"passed_time":0.8326373699,"remaining_time":2.357544124},
{"learn":[1168.601277],"iteration":261,"passed_time":0.835512491,"remaining_time":2.353466482},
{"learn":[1167.825877],"iteration":262,"passed_time":0.8384427443,"remaining_time":2.349552481},
{"learn":[1167.098828],"iteration":263,"passed_time":0.8409657638,"remaining_time":2.344510614},
{"learn":[1166.323468],"iteration":264,"passed_time":0.8434632759,"remaining_time":2.339417011},
{"learn":[1165.460166],"iteration":265,"passed_time":0.845799383,"remaining_time":2.333897546},
{"learn":[1164.641187],"iteration":266,"passed_time":0.84778548,"remaining_time":2.327441037},
{"learn":[1163.524791],"iteration":267,"passed_time":0.8495804555,"remaining_time":2.320495871},
{"learn":[1158.998424],"iteration":268,"passed_time":0.8522271016,"remaining_time":2.315903388},
{"learn":[1155.076967],"iteration":269,"passed_time":0.8552607853,"remaining_time":2.312371753},
{"learn":[1153.600344],"iteration":270,"passed_time":0.8579260457,"remaining_time":2.307852721},
{"learn":[1152.599721],"iteration":271,"passed_time":0.8607365496,"remaining_time":2.303736059},
{"learn":[1151.95659],"iteration":272,"passed_time":0.8631926539,"remaining_time":2.298685199},
{"learn":[1151.19394],"iteration":273,"passed_time":0.8655074057,"remaining_time":2.293278746},
{"learn":[1148.720463],"iteration":274,"passed_time":0.868625406,"remaining_time":2.290012434},
{"learn":[1148.01942],"iteration":275,"passed_time":0.8709216821,"remaining_time":2.284591659},
{"learn":[1147.014547],"iteration":276,"passed_time":0.8722746901,"remaining_time":2.276731411},
{"learn":[1146.261694],"iteration":277,"passed_time":0.8747148928,"remaining_time":2.271741556},
{"learn":[1145.661121],"iteration":278,"passed_time":0.8772997067,"remaining_time":2.267143687},
{"learn":[1144.990076],"iteration":279,"passed_time":0.8802018668,"remaining_time":2.263376229},
{"learn":[1140.864304],"iteration":280,"passed_time":0.882976024,"remaining_time":2.259287407},
{"learn":[1137.354729],"iteration":281,"passed_time":0.8858571966,"remaining_time":2.25548038},
{"learn":[1136.801681],"iteration":282,"passed_time":0.8887064925,"remaining_time":2.251599135},
{"learn":[1135.839148],"iteration":283,"passed_time":0.8914934201,"remaining_time":2.247567918},
{"learn":[1130.967534],"iteration":284,"passed_time":0.8934585556,"remaining_time":2.241483745},
{"learn":[1130.432582],"iteration":285,"passed_time":0.8964076682,"remaining_time":2.237884878},
{"learn":[1129.875989],"iteration":286,"passed_time":0.8989270309,"remaining_time":2.233222902},
{"learn":[1129.302099],"iteration":287,"passed_time":0.9017301183,"remaining_time":2.229277237},
{"learn":[1128.765161],"iteration":288,"passed_time":0.9035891706,"remaining_time":2.223016956},
{"learn":[1125.135152],"iteration":289,"passed_time":0.905865911,"remaining_time":2.217809644},
{"learn":[1121.761671],"iteration":290,"passed_time":0.9077430182,"remaining_time":2.211648797},
{"learn":[1121.284904],"iteration":291,"passed_time":0.910201737,"remaining_time":2.206927499},
{"learn":[1120.497302],"iteration":292,"passed_time":0.9127362703,"remaining_time":2.202404584},
{"learn":[1118.432746],"iteration":293,"passed_time":0.9154099452,"remaining_time":2.198229324},
{"learn":[1114.386566],"iteration":294,"passed_time":0.9182364819,"remaining_time":2.194429559},
{"learn":[1111.788647],"iteration":295,"passed_time":0.9212791688,"remaining_time":2.191150456},
{"learn":[1110.903619],"iteration":296,"passed_time":0.9241723737,"remaining_time":2.18751912},
{"learn":[1110.379375],"iteration":297,"passed_time":0.9270254894,"remaining_time":2.1837983},
{"learn":[1109.530812],"iteration":298,"passed_time":0.9299539425,"remaining_time":2.180259912},
{"learn":[1106.591561],"iteration":299,"passed_time":0.9326345278,"remaining_time":2.176147232},
{"learn":[1104.857302],"iteration":300,"passed_time":0.9355351674,"remaining_time":2.17255509},
{"learn":[1104.03306],"iteration":301,"passed_time":0.9384671332,"remaining_time":2.16903993},
{"learn":[1103.441978],"iteration":302,"passed_time":0.9421242158,"remaining_time":2.167196628},
{"learn":[1102.947346],"iteration":303,"passed_time":0.9446337412,"remaining_time":2.162714092},
{"learn":[1102.536281],"iteration":304,"passed_time":0.9465093952,"remaining_time":2.156800097},
{"learn":[1102.156764],"iteration":305,"passed_time":0.9485733878,"remaining_time":2.151339644},
{"learn":[1098.328753],"iteration":306,"passed_time":0.9503832613,"remaining_time":2.145327687},
{"learn":[1097.945565],"iteration":307,"passed_time":0.952167543,"remaining_time":2.139285519},
{"learn":[1096.371401],"iteration":308,"passed_time":0.9539067291,"remaining_time":2.133170064},
{"learn":[1095.94453],"iteration":309,"passed_time":0.9564826607,"remaining_time":2.128945277},
{"learn":[1092.706919],"iteration":310,"passed_time":0.958810686,"remaining_time":2.124181873},
{"learn":[1091.900333],"iteration":311,"passed_time":0.9613892105,"remaining_time":2.119986464},
{"learn":[1088.929808],"iteration":312,"passed_time":0.9641245752,"remaining_time":2.116145633},
{"learn":[1088.493091],"iteration":313,"passed_time":0.9668819465,"remaining_time":2.112359921},
{"learn":[1087.342847],"iteration":314,"passed_time":0.9680730973,"remaining_time":2.105174831},
{"learn":[1086.81077],"iteration":315,"passed_time":0.9708180271,"remaining_time":2.101390919},
{"learn":[1086.08089],"iteration":316,"passed_time":0.9732560013,"remaining_time":2.096952205},
{"learn":[1085.666597],"iteration":317,"passed_time":0.97568954,"remaining_time":2.092516561},
{"learn":[1084.1051],"iteration":318,"passed_time":0.977835548,"remaining_time":2.08747965},
{"learn":[1083.401297],"iteration":319,"passed_time":0.9798813249,"remaining_time":2.082247815},
{"learn":[1077.152986],"iteration":320,"passed_time":0.9820423851,"remaining_time":2.077279687},
{"learn":[1076.727096],"iteration":321,"passed_time":0.984041027,"remaining_time":2.071987007},
{"learn":[1076.099199],"iteration":322,"passed_time":0.9866241413,"remaining_time":2.067939764},
{"learn":[1072.34095],"iteration":323,"passed_time":0.9895309147,"remaining_time":2.064576847},
{"learn":[1067.351551],"iteration":324,"passed_time":0.992090252,"remaining_time":2.060495139},
{"learn":[1064.077026],"iteration":325,"passed_time":0.9949771492,"remaining_time":2.057099996},
{"learn":[1060.970056],"iteration":326,"passed_time":0.9978479213,"remaining_time":2.053674774},
{"learn":[1060.522866],"iteration":327,"passed_time":1.000148131,"remaining_time":2.049083976},
{"learn":[1057.520165],"iteration":328,"passed_time":1.003287288,"remaining_time":2.046218147},
{"learn":[1056.38467],"iteration":329,"passed_time":1.005986822,"remaining_time":2.042458094},
{"learn":[1055.509242],"iteration":330,"passed_time":1.00854222,"remaining_time":2.038413128},
{"learn":[1054.526172],"iteration":331,"passed_time":1.010853667,"remaining_time":2.033886294},
{"learn":[1050.755353],"iteration":332,"passed_time":1.012174385,"remaining_time":2.027388333},
{"learn":[1047.764516],"iteration":333,"passed_time":1.013414837,"remaining_time":2.020761322},
{"learn":[1046.09558],"iteration":334,"passed_time":1.016243165,"remaining_time":2.017318521},
{"learn":[1042.940722],"iteration":335,"passed_time":1.018333072,"remaining_time":2.012420119},
{"learn":[1040.920139],"iteration":336,"passed_time":1.021350161,"remaining_time":2.009362484},
{"learn":[1040.278336],"iteration":337,"passed_time":1.024034254,"remaining_time":2.005652887},
{"learn":[1039.956846],"iteration":338,"passed_time":1.025983485,"remaining_time":2.000516471},
{"learn":[1037.96954],"iteration":339,"passed_time":1.028284571,"remaining_time":1.996081814},
{"learn":[1036.010421],"iteration":340,"passed_time":1.030290714,"remaining_time":1.991089679},
{"learn":[1035.138297],"iteration":341,"passed_time":1.032899503,"remaining_time":1.987274482},
{"learn":[1034.060045],"iteration":342,"passed_time":1.035484187,"remaining_time":1.983420149},
{"learn":[1033.439481],"iteration":343,"passed_time":1.037027415,"remaining_time":1.977587163},
{"learn":[1029.92292],"iteration":344,"passed_time":1.039767267,"remaining_time":1.974050899},
{"learn":[1026.746672],"iteration":345,"passed_time":1.042146404,"remaining_time":1.969837422},
{"learn":[1023.530612],"iteration":346,"passed_time":1.043944759,"remaining_time":1.964541577},
{"learn":[1022.975685],"iteration":347,"passed_time":1.046469456,"remaining_time":1.960626682},
{"learn":[1022.741977],"iteration":348,"passed_time":1.049317648,"remaining_time":1.957323177},
{"learn":[1021.797514],"iteration":349,"passed_time":1.051903467,"remaining_time":1.95353501},
{"learn":[1019.814741],"iteration":350,"passed_time":1.054861923,"remaining_time":1.9504427},
{"learn":[1018.91296],"iteration":351,"passed_time":1.056379842,"remaining_time":1.944699255},
{"learn":[1018.602309],"iteration":352,"passed_time":1.058316545,"remaining_time":1.939747322},
{"learn":[1018.216575],"iteration":353,"passed_time":1.060864732,"remaining_time":1.935928297},
{"learn":[1016.099385],"iteration":354,"passed_time":1.063368142,"remaining_time":1.932035074},
{"learn":[1015.813838],"iteration":355,"passed_time":1.066130458,"remaining_time":1.928618019},
{"learn":[1012.753907],"iteration":356,"passed_time":1.068532031,"remaining_time":1.92455489},
{"learn":[1012.472269],"iteration":357,"passed_time":1.071297214,"remaining_time":1.921153105},
{"learn":[1010.850976],"iteration":358,"passed_time":1.074008152,"remaining_time":1.917658009},
{"learn":[1010.244197],"iteration":359,"passed_time":1.075259618,"remaining_time":1.911572654},
{"learn":[1009.490223],"iteration":360,"passed_time":1.07824904,"remaining_time":1.908590406},
{"learn":[1007.597243],"iteration":361,"passed_time":1.080894393,"remaining_time":1.90500172},
{"learn":[1003.70543],"iteration":362,"passed_time":1.082523828,"remaining_time":1.899635478},
{"learn":[1000.414936],"iteration":363,"passed_time":1.085212756,"remaining_time":1.896140969},
{"learn":[996.8245395],"iteration":364,"passed_time":1.087557239,"remaining_time":1.892051635},
{"learn":[994.4077698],"iteration":365,"passed_time":1.089387508,"remaining_time":1.887081093},
{"learn":[992.3661895],"iteration":366,"passed_time":1.092043934,"remaining_time":1.883552616},
{"learn":[991.8009011],"iteration":367,"passed_time":1.094220478,"remaining_time":1.879204734},
{"learn":[991.2974224],"iteration":368,"passed_time":1.096907101,"remaining_time":1.875740869},
{"learn":[988.5118545],"iteration":369,"passed_time":1.099516584,"remaining_time":1.872149859},
{"learn":[984.9584812],"iteration":370,"passed_time":1.101614617,"remaining_time":1.867697019},
{"learn":[983.036121],"iteration":371,"passed_time":1.104274876,"remaining_time":1.864205973},
{"learn":[980.2500028],"iteration":372,"passed_time":1.106266652,"remaining_time":1.859595686},
{"learn":[979.5299551],"iteration":373,"passed_time":1.108592154,"remaining_time":1.855557991},
{"learn":[976.0025725],"iteration":374,"passed_time":1.111552839,"remaining_time":1.852588065},
{"learn":[972.7306982],"iteration":375,"passed_time":1.113425614,"remaining_time":1.84781272},
{"learn":[969.3252507],"iteration":376,"passed_time":1.115353085,"remaining_time":1.843143161},
{"learn":[968.7762728],"iteration":377,"passed_time":1.117974657,"remaining_time":1.839630255},
{"learn":[965.1241447],"iteration":378,"passed_time":1.120049999,"remaining_time":1.835227043},
{"learn":[964.8696285],"iteration":379,"passed_time":1.122065604,"remaining_time":1.830738616},
{"learn":[963.9801468],"iteration":380,"passed_time":1.125076834,"remaining_time":1.827880735},
{"learn":[963.534131],"iteration":381,"passed_time":1.12740818,"remaining_time":1.823922134},
{"learn":[961.525906],"iteration":382,"passed_time":1.130227058,"remaining_time":1.820757427},
{"learn":[957.9364297],"iteration":383,"passed_time":1.134061948,"remaining_time":1.819224374},
{"learn":[955.0301062],"iteration":384,"passed_time":1.136521716,"remaining_time":1.815482741},
{"learn":[952.8350027],"iteration":385,"passed_time":1.138902888,"remaining_time":1.811622729},
{"learn":[952.2424366],"iteration":386,"passed_time":1.141105112,"remaining_time":1.807486909},
{"learn":[948.3893313],"iteration":387,"passed_time":1.143200461,"remaining_time":1.803192479},
{"learn":[947.5920893],"iteration":388,"passed_time":1.145507077,"remaining_time":1.799241193},
{"learn":[947.1678627],"iteration":389,"passed_time":1.148124373,"remaining_time":1.795784275},
{"learn":[944.8728715],"iteration":390,"passed_time":1.151051498,"remaining_time":1.792814226},
{"learn":[944.6140719],"iteration":391,"passed_time":1.152778835,"remaining_time":1.7879835},
{"learn":[940.5944758],"iteration":392,"passed_time":1.154446496,"remaining_time":1.783076395},
{"learn":[937.9182612],"iteration":393,"passed_time":1.156087397,"remaining_time":1.778144576},
{"learn":[935.1231887],"iteration":394,"passed_time":1.158796536,"remaining_time":1.77486558},
{"learn":[934.873526],"iteration":395,"passed_time":1.161739167,"remaining_time":1.771945598},
{"learn":[933.3980016],"iteration":396,"passed_time":1.164522716,"remaining_time":1.768783873},
{"learn":[930.8960417],"iteration":397,"passed_time":1.166743761,"remaining_time":1.764773226},
{"learn":[927.547551],"iteration":398,"passed_time":1.16890939,"remaining_time":1.760688079},
{"learn":[926.9198716],"iteration":399,"passed_time":1.171550436,"remaining_time":1.757325655},
{"learn":[924.3067046],"iteration":400,"passed_time":1.174292648,"remaining_time":1.754117946},
{"learn":[921.4155801],"iteration":401,"passed_time":1.176831383,"remaining_time":1.750609869},
{"learn":[918.8619139],"iteration":402,"passed_time":1.178913088,"remaining_time":1.746429563},
{"learn":[915.1487691],"iteration":403,"passed_time":1.181410606,"remaining_time":1.742873073},
{"learn":[914.6647914],"iteration":404,"passed_time":1.183546366,"remaining_time":1.73879034},
{"learn":[911.6596051],"iteration":405,"passed_time":1.185768568,"remaining_time":1.734843669},
{"learn":[909.8674355],"iteration":406,"passed_time":1.188501606,"remaining_time":1.73164976},
{"learn":[909.4984724],"iteration":407,"passed_time":1.190354242,"remaining_time":1.727180664},
{"learn":[905.7870736],"iteration":408,"passed_time":1.192840403,"remaining_time":1.7236398},
{"learn":[904.5311284],"iteration":409,"passed_time":1.195503683,"remaining_time":1.720358958},
{"learn":[902.5222525],"iteration":410,"passed_time":1.19728754,"remaining_time":1.71582083},
{"learn":[902.2985397],"iteration":411,"passed_time":1.199601069,"remaining_time":1.712052011},
{"learn":[900.8062025],"iteration":412,"passed_time":1.202381898,"remaining_time":1.708954417},
{"learn":[898.8321017],"iteration":413,"passed_time":1.205001214,"remaining_time":1.705629737},
{"learn":[895.8284168],"iteration":414,"passed_time":1.208002797,"remaining_time":1.702847317},
{"learn":[893.2211428],"iteration":415,"passed_time":1.210591596,"remaining_time":1.699484356},
{"learn":[892.2940568],"iteration":416,"passed_time":1.21304412,"remaining_time":1.695934585},
{"learn":[892.0868322],"iteration":417,"passed_time":1.214580912,"remaining_time":1.691115049},
{"learn":[891.1320877],"iteration":418,"passed_time":1.217319933,"remaining_time":1.687978236},
{"learn":[890.9169948],"iteration":419,"passed_time":1.219951247,"remaining_time":1.684694579},
{"learn":[888.5486156],"iteration":420,"passed_time":1.222638454,"remaining_time":1.681490891},
{"learn":[885.895291],"iteration":421,"passed_time":1.225142449,"remaining_time":1.67803871},
{"learn":[883.0235237],"iteration":422,"passed_time":1.227922367,"remaining_time":1.67496739},
{"learn":[880.4865053],"iteration":423,"passed_time":1.230512921,"remaining_time":1.671640195},
{"learn":[879.5822858],"iteration":424,"passed_time":1.233219887,"remaining_time":1.668473964},
{"learn":[876.6789855],"iteration":425,"passed_time":1.23576234,"remaining_time":1.665088224},
{"learn":[875.4557826],"iteration":426,"passed_time":1.238479225,"remaining_time":1.661940505},
{"learn":[875.2951348],"iteration":427,"passed_time":1.24122045,"remaining_time":1.65882733},
{"learn":[875.0733622],"iteration":428,"passed_time":1.243476084,"remaining_time":1.655069567},
{"learn":[872.2233974],"iteration":429,"passed_time":1.245612502,"remaining_time":1.651160758},
{"learn":[871.0094666],"iteration":430,"passed_time":1.248357758,"remaining_time":1.648063954},
{"learn":[869.3934944],"iteration":431,"passed_time":1.251067387,"remaining_time":1.644921934},
{"learn":[866.9122206],"iteration":432,"passed_time":1.253986218,"remaining_time":1.642055856},
{"learn":[864.4261307],"iteration":433,"passed_time":1.256690381,"remaining_time":1.638909575},
{"learn":[862.3745083],"iteration":434,"passed_time":1.259458132,"remaining_time":1.635847918},
{"learn":[860.0678776],"iteration":435,"passed_time":1.261482622,"remaining_time":1.631826144},
{"learn":[857.6853769],"iteration":436,"passed_time":1.264221914,"remaining_time":1.628734411},
{"learn":[857.140248],"iteration":437,"passed_time":1.266942919,"remaining_time":1.625620823},
{"learn":[856.5879515],"iteration":438,"passed_time":1.269550459,"remaining_time":1.622364026},
{"learn":[854.2400768],"iteration":439,"passed_time":1.272107445,"remaining_time":1.619045839},
{"learn":[853.5252075],"iteration":440,"passed_time":1.274888236,"remaining_time":1.616014793},
{"learn":[852.5207253],"iteration":441,"passed_time":1.277202777,"remaining_time":1.612396266},
{"learn":[850.3485515],"iteration":442,"passed_time":1.279899515,"remaining_time":1.609264176},
{"learn":[849.8632291],"iteration":443,"passed_time":1.28277557,"remaining_time":1.606358597},
{"learn":[847.8609179],"iteration":444,"passed_time":1.285434863,"remaining_time":1.603182806},
{"learn":[845.9747731],"iteration":445,"passed_time":1.288075801,"remaining_time":1.599986533},
{"learn":[843.6608332],"iteration":446,"passed_time":1.290495853,"remaining_time":1.596519478},
{"learn":[842.0646498],"iteration":447,"passed_time":1.292427392,"remaining_time":1.592455179},
{"learn":[840.0358663],"iteration":448,"passed_time":1.295226691,"remaining_time":1.589465272},
{"learn":[837.778776],"iteration":449,"passed_time":1.298138521,"remaining_time":1.586613748},
{"learn":[835.7923591],"iteration":450,"passed_time":1.300767262,"remaining_time":1.583417354},
{"learn":[833.0101866],"iteration":451,"passed_time":1.303399108,"remaining_time":1.580227237},
{"learn":[830.4658563],"iteration":452,"passed_time":1.305893275,"remaining_time":1.576873337},
{"learn":[830.333175],"iteration":453,"passed_time":1.308559051,"remaining_time":1.573729608},
{"learn":[828.1849094],"iteration":454,"passed_time":1.311297855,"remaining_time":1.570675452},
{"learn":[826.6391556],"iteration":455,"passed_time":1.313852496,"remaining_time":1.567402978},
{"learn":[825.031131],"iteration":456,"passed_time":1.316478297,"remaining_time":1.564218195},
{"learn":[824.7355098],"iteration":457,"passed_time":1.319221028,"remaining_time":1.561174229},
{"learn":[824.032982],"iteration":458,"passed_time":1.322590123,"remaining_time":1.558869839},
{"learn":[822.9227946],"iteration":459,"passed_time":1.325883588,"remaining_time":1.556472039},
{"learn":[820.928022],"iteration":460,"passed_time":1.327994162,"remaining_time":1.552687317},
{"learn":[820.0046725],"iteration":461,"passed_time":1.330392814,"remaining_time":1.549245312},
{"learn":[817.9326145],"iteration":462,"passed_time":1.332943508,"remaining_time":1.545984156},
{"learn":[816.555267],"iteration":463,"passed_time":1.33585842,"remaining_time":1.543146796},
{"learn":[816.0822253],"iteration":464,"passed_time":1.33782855,"remaining_time":1.539222095},
{"learn":[815.8857595],"iteration":465,"passed_time":1.340193457,"remaining_time":1.535758167},
{"learn":[814.7926623],"iteration":466,"passed_time":1.342994127,"remaining_time":1.532796295},
{"learn":[814.6262911],"iteration":467,"passed_time":1.345866008,"remaining_time":1.52991606},
{"learn":[813.9559274],"iteration":468,"passed_time":1.348593479,"remaining_time":1.526872361},
{"learn":[811.9280621],"iteration":469,"passed_time":1.351349971,"remaining_time":1.523862734},
{"learn":[809.1815979],"iteration":470,"passed_time":1.353280929,"remaining_time":1.519926988},
{"learn":[809.0188255],"iteration":471,"passed_time":1.355849916,"remaining_time":1.516713466},
{"learn":[807.0023558],"iteration":472,"passed_time":1.358845464,"remaining_time":1.513977927},
{"learn":[806.7743608],"iteration":473,"passed_time":1.361533295,"remaining_time":1.510899816},
{"learn":[806.5211657],"iteration":474,"passed_time":1.364325448,"remaining_time":1.507938653},
{"learn":[806.3538801],"iteration":475,"passed_time":1.366947031,"remaining_time":1.504790429},
{"learn":[804.5475056],"iteration":476,"passed_time":1.369066732,"remaining_time":1.501094132},
{"learn":[802.9206129],"iteration":477,"passed_time":1.371738254,"remaining_time":1.498007048},
{"learn":[802.499008],"iteration":478,"passed_time":1.374403039,"remaining_time":1.49491437},
{"learn":[800.7054452],"iteration":479,"passed_time":1.376979567,"remaining_time":1.491727864},
{"learn":[799.0408993],"iteration":480,"passed_time":1.379347939,"remaining_time":1.488319294},
{"learn":[797.6364594],"iteration":481,"passed_time":1.381973156,"remaining_time":1.485191069},
{"learn":[795.4960606],"iteration":482,"passed_time":1.384657307,"remaining_time":1.482128008},
{"learn":[794.0657562],"iteration":483,"passed_time":1.387342773,"remaining_time":1.479067915},
{"learn":[792.21642],"iteration":484,"passed_time":1.390021271,"remaining_time":1.476001969},
{"learn":[791.7839854],"iteration":485,"passed_time":1.392696993,"remaining_time":1.472934679},
{"learn":[789.7955565],"iteration":486,"passed_time":1.395323752,"remaining_time":1.469817423},
{"learn":[788.7421984],"iteration":487,"passed_time":1.397941801,"remaining_time":1.466693037},
{"learn":[786.6838579],"iteration":488,"passed_time":1.400626689,"remaining_time":1.463640568},
{"learn":[786.1499151],"iteration":489,"passed_time":1.402507143,"remaining_time":1.459752333},
{"learn":[784.7810698],"iteration":490,"passed_time":1.405229821,"remaining_time":1.456745374},
{"learn":[783.9892869],"iteration":491,"passed_time":1.407865646,"remaining_time":1.453649894},
{"learn":[782.1436806],"iteration":492,"passed_time":1.410524394,"remaining_time":1.450579854},
{"learn":[781.5330303],"iteration":493,"passed_time":1.413012508,"remaining_time":1.447336698},
{"learn":[780.0596334],"iteration":494,"passed_time":1.415925486,"remaining_time":1.444530042},
{"learn":[778.6910125],"iteration":495,"passed_time":1.417850813,"remaining_time":1.440719374},
{"learn":[777.7725079],"iteration":496,"passed_time":1.420264159,"remaining_time":1.437410205},
{"learn":[776.2305906],"iteration":497,"passed_time":1.422949257,"remaining_time":1.434378568},
{"learn":[773.7981947],"iteration":498,"passed_time":1.425553175,"remaining_time":1.431266815},
{"learn":[773.0635777],"iteration":499,"passed_time":1.428365997,"remaining_time":1.428365997},
{"learn":[771.8384046],"iteration":500,"passed_time":1.431012379,"remaining_time":1.425299754},
{"learn":[770.0166833],"iteration":501,"passed_time":1.433938183,"remaining_time":1.42251238},
{"learn":[768.6208805],"iteration":502,"passed_time":1.436722392,"remaining_time":1.41958455},
{"learn":[767.2505396],"iteration":503,"passed_time":1.439081823,"remaining_time":1.416239254},
{"learn":[766.671338],"iteration":504,"passed_time":1.44178659,"remaining_time":1.413236361},
{"learn":[765.3637345],"iteration":505,"passed_time":1.444484114,"remaining_time":1.410227573},
{"learn":[762.9357823],"iteration":506,"passed_time":1.44664686,"remaining_time":1.406700004},
{"learn":[761.3184963],"iteration":507,"passed_time":1.448502983,"remaining_time":1.402880842},
{"learn":[759.9847757],"iteration":508,"passed_time":1.450439616,"remaining_time":1.399147055},
{"learn":[759.207082],"iteration":509,"passed_time":1.452184136,"remaining_time":1.395235738},
{"learn":[757.5974775],"iteration":510,"passed_time":1.454605277,"remaining_time":1.391980392},
{"learn":[756.4763525],"iteration":511,"passed_time":1.457235439,"remaining_time":1.388927528},
{"learn":[755.516571],"iteration":512,"passed_time":1.45956152,"remaining_time":1.385587642},
{"learn":[753.3952752],"iteration":513,"passed_time":1.461836023,"remaining_time":1.382202932},
{"learn":[751.5331949],"iteration":514,"passed_time":1.464600181,"remaining_time":1.379283665},
{"learn":[750.1240767],"iteration":515,"passed_time":1.467112492,"remaining_time":1.376128772},
{"learn":[748.3738172],"iteration":516,"passed_time":1.46994741,"remaining_time":1.373277754},
{"learn":[746.9963455],"iteration":517,"passed_time":1.472274461,"remaining_time":1.369954228},
{"learn":[746.3607967],"iteration":518,"passed_time":1.475045616,"remaining_time":1.367046129},
{"learn":[745.1370382],"iteration":519,"passed_time":1.477647126,"remaining_time":1.363981962},
{"learn":[744.4925205],"iteration":520,"passed_time":1.479913452,"remaining_time":1.360611408},
{"learn":[743.3501967],"iteration":521,"passed_time":1.483206576,"remaining_time":1.358185332},
{"learn":[742.4280578],"iteration":522,"passed_time":1.485334487,"remaining_time":1.354693213},
{"learn":[741.0260812],"iteration":523,"passed_time":1.487829747,"remaining_time":1.35154},
{"learn":[740.6599362],"iteration":524,"passed_time":1.490420306,"remaining_time":1.348475515},
{"learn":[739.4158928],"iteration":525,"passed_time":1.492613606,"remaining_time":1.345054847},
{"learn":[737.8498942],"iteration":526,"passed_time":1.494930472,"remaining_time":1.341749741},
{"learn":[736.2871741],"iteration":527,"passed_time":1.497486048,"remaining_time":1.33866177},
{"learn":[735.4106096],"iteration":528,"passed_time":1.499667902,"remaining_time":1.335243065},
{"learn":[733.8327603],"iteration":529,"passed_time":1.501954094,"remaining_time":1.331921555},
{"learn":[732.1853491],"iteration":530,"passed_time":1.503600065,"remaining_time":1.328038476},
{"learn":[731.9972776],"iteration":531,"passed_time":1.505696289,"remaining_time":1.324559893},
{"learn":[731.2796505],"iteration":532,"passed_time":1.507851871,"remaining_time":1.321138506},
{"learn":[730.2756342],"iteration":533,"passed_time":1.510379805,"remaining_time":1.318046796},
{"learn":[729.2205034],"iteration":534,"passed_time":1.512911085,"remaining_time":1.314960102},
{"learn":[728.7238387],"iteration":535,"passed_time":1.515780148,"remaining_time":1.312167889},
{"learn":[726.7871523],"iteration":536,"passed_time":1.518101694,"remaining_time":1.308903322},
{"learn":[725.1795166],"iteration":537,"passed_time":1.521692077,"remaining_time":1.306731858},
{"learn":[723.4542516],"iteration":538,"passed_time":1.524610535,"remaining_time":1.303980439},
{"learn":[722.5492038],"iteration":539,"passed_time":1.526138046,"remaining_time":1.30004352},
{"learn":[721.7803535],"iteration":540,"passed_time":1.527885166,"remaining_time":1.296301832},
{"learn":[720.4136297],"iteration":541,"passed_time":1.529597346,"remaining_time":1.292537979},
{"learn":[718.6827282],"iteration":542,"passed_time":1.53119981,"remaining_time":1.288689343},
{"learn":[717.0572014],"iteration":543,"passed_time":1.533081738,"remaining_time":1.285083222},
{"learn":[715.392196],"iteration":544,"passed_time":1.535224751,"remaining_time":1.281701398},
{"learn":[713.6513741],"iteration":545,"passed_time":1.537181618,"remaining_time":1.278169331},
{"learn":[713.1106218],"iteration":546,"passed_time":1.538480686,"remaining_time":1.274098264},
{"learn":[712.5412871],"iteration":547,"passed_time":1.5399963,"remaining_time":1.270215926},
{"learn":[710.5932561],"iteration":548,"passed_time":1.542313057,"remaining_time":1.267000344},
{"learn":[710.2067274],"iteration":549,"passed_time":1.54518508,"remaining_time":1.264242338},
{"learn":[708.4950599],"iteration":550,"passed_time":1.547485669,"remaining_time":1.261018268},
{"learn":[708.1980247],"iteration":551,"passed_time":1.550206094,"remaining_time":1.258138279},
{"learn":[706.5381273],"iteration":552,"passed_time":1.552581175,"remaining_time":1.25497972},
{"learn":[704.4992394],"iteration":553,"passed_time":1.554549832,"remaining_time":1.251496796},
{"learn":[703.6111764],"iteration":554,"passed_time":1.555962452,"remaining_time":1.247573498},
{"learn":[703.2805194],"iteration":555,"passed_time":1.557357031,"remaining_time":1.243644823},
{"learn":[701.8897693],"iteration":556,"passed_time":1.559933711,"remaining_time":1.240665411},
{"learn":[700.6152369],"iteration":557,"passed_time":1.562317114,"remaining_time":1.237534344},
{"learn":[699.5699771],"iteration":558,"passed_time":1.565100057,"remaining_time":1.234721154},
{"learn":[698.0319538],"iteration":559,"passed_time":1.567407567,"remaining_time":1.231534517},
{"learn":[697.7355624],"iteration":560,"passed_time":1.569334828,"remaining_time":1.228053457},
{"learn":[696.2140626],"iteration":561,"passed_time":1.570921836,"remaining_time":1.224312748},
{"learn":[695.5951236],"iteration":562,"passed_time":1.57290246,"remaining_time":1.220885213},
{"learn":[694.1134563],"iteration":563,"passed_time":1.575352772,"remaining_time":1.217825902},
{"learn":[692.849194],"iteration":564,"passed_time":1.577955494,"remaining_time":1.214886088},
{"learn":[692.2502964],"iteration":565,"passed_time":1.58097089,"remaining_time":1.212263898},
{"learn":[691.0191052],"iteration":566,"passed_time":1.582924119,"remaining_time":1.208829177},
{"learn":[689.7650132],"iteration":567,"passed_time":1.584512566,"remaining_time":1.205122233},
{"learn":[688.9712557],"iteration":568,"passed_time":1.586001121,"remaining_time":1.20134707},
{"learn":[687.5268632],"iteration":569,"passed_time":1.587281541,"remaining_time":1.197422917},
{"learn":[685.9930434],"iteration":570,"passed_time":1.589026103,"remaining_time":1.193856739},
{"learn":[685.4146273],"iteration":571,"passed_time":1.59121676,"remaining_time":1.190630723},
{"learn":[684.9906841],"iteration":572,"passed_time":1.593885214,"remaining_time":1.187764374},
{"learn":[683.4497393],"iteration":573,"passed_time":1.595913076,"remaining_time":1.184423293},
{"learn":[681.9560145],"iteration":574,"passed_time":1.598597918,"remaining_time":1.181572374},
{"learn":[680.787668],"iteration":575,"passed_time":1.600264074,"remaining_time":1.177972165},
{"learn":[680.204197],"iteration":576,"passed_time":1.602083191,"remaining_time":1.174490797},
{"learn":[679.4367137],"iteration":577,"passed_time":1.604258252,"remaining_time":1.171275056},
{"learn":[678.9889829],"iteration":578,"passed_time":1.606878703,"remaining_time":1.16838676},
{"learn":[677.5349769],"iteration":579,"passed_time":1.609304161,"remaining_time":1.165358185},
{"learn":[677.0414246],"iteration":580,"passed_time":1.612109908,"remaining_time":1.162605941},
{"learn":[676.0470224],"iteration":581,"passed_time":1.614192582,"remaining_time":1.159334191},
{"learn":[675.7194704],"iteration":582,"passed_time":1.615808552,"remaining_time":1.155732703},
{"learn":[674.9014508],"iteration":583,"passed_time":1.618275585,"remaining_time":1.152744252},
{"learn":[673.6166508],"iteration":584,"passed_time":1.621030673,"remaining_time":1.14996193},
{"learn":[672.4247581],"iteration":585,"passed_time":1.623545043,"remaining_time":1.147009638},
{"learn":[670.9743296],"iteration":586,"passed_time":1.625047808,"remaining_time":1.143347095},
{"learn":[669.9973919],"iteration":587,"passed_time":1.62738953,"remaining_time":1.140279739},
{"learn":[669.3815188],"iteration":588,"passed_time":1.629523265,"remaining_time":1.137069715},
{"learn":[668.7542253],"iteration":589,"passed_time":1.631077917,"remaining_time":1.133460925},
{"learn":[668.0215355],"iteration":590,"passed_time":1.633531195,"remaining_time":1.130480979},
{"learn":[667.0168484],"iteration":591,"passed_time":1.636096259,"remaining_time":1.127579854},
{"learn":[665.3724103],"iteration":592,"passed_time":1.637906646,"remaining_time":1.124161897},
{"learn":[663.7477251],"iteration":593,"passed_time":1.6406408,"remaining_time":1.121380749},
{"learn":[663.2193152],"iteration":594,"passed_time":1.643353995,"remaining_time":1.118585493},
{"learn":[662.2354296],"iteration":595,"passed_time":1.644917302,"remaining_time":1.115011057},
{"learn":[660.9170448],"iteration":596,"passed_time":1.646707904,"remaining_time":1.111596793},
{"learn":[659.5353076],"iteration":597,"passed_time":1.648478108,"remaining_time":1.108174246},
{"learn":[658.6013768],"iteration":598,"passed_time":1.6507054,"remaining_time":1.105063214},
{"learn":[657.9353728],"iteration":599,"passed_time":1.653205738,"remaining_time":1.102137159},
{"learn":[656.5279317],"iteration":600,"passed_time":1.655679986,"remaining_time":1.099195198},
{"learn":[655.6837565],"iteration":601,"passed_time":1.658415055,"remaining_time":1.096427229},
{"learn":[654.5307357],"iteration":602,"passed_time":1.660653457,"remaining_time":1.093332376},
{"learn":[653.4100531],"iteration":603,"passed_time":1.662583671,"remaining_time":1.090038301},
{"learn":[652.8809297],"iteration":604,"passed_time":1.664481728,"remaining_time":1.08672774},
{"learn":[651.5532871],"iteration":605,"passed_time":1.666824924,"remaining_time":1.083711254},
{"learn":[650.7336783],"iteration":606,"passed_time":1.668546063,"remaining_time":1.080294239},
{"learn":[649.9606147],"iteration":607,"passed_time":1.671011686,"remaining_time":1.077362798},
{"learn":[648.9131052],"iteration":608,"passed_time":1.673291147,"remaining_time":1.074313364},
{"learn":[647.5622521],"iteration":609,"passed_time":1.675436201,"remaining_time":1.071180522},
{"learn":[647.0088846],"iteration":610,"passed_time":1.676978854,"remaining_time":1.067667389},
{"learn":[645.298629],"iteration":611,"passed_time":1.679182768,"remaining_time":1.064579925},
{"learn":[644.6023968],"iteration":612,"passed_time":1.681011436,"remaining_time":1.061258443},
{"learn":[644.1795835],"iteration":613,"passed_time":1.683555422,"remaining_time":1.05839152},
{"learn":[643.2687643],"iteration":614,"passed_time":1.685435865,"remaining_time":1.055110257},
{"learn":[642.0147249],"iteration":615,"passed_time":1.687597053,"remaining_time":1.052008552},
{"learn":[641.2663242],"iteration":616,"passed_time":1.690061448,"remaining_time":1.049098111},
{"learn":[639.9493213],"iteration":617,"passed_time":1.691863833,"remaining_time":1.045779909},
{"learn":[638.7186406],"iteration":618,"passed_time":1.694549458,"remaining_time":1.043010248},
{"learn":[637.5271263],"iteration":619,"passed_time":1.697241803,"remaining_time":1.040244976},
{"learn":[636.6191309],"iteration":620,"passed_time":1.69988986,"remaining_time":1.03745291},
{"learn":[636.0261446],"iteration":621,"passed_time":1.701898979,"remaining_time":1.034273013},
{"learn":[635.1614564],"iteration":622,"passed_time":1.703356972,"remaining_time":1.030763368},
{"learn":[633.690377],"iteration":623,"passed_time":1.706522928,"remaining_time":1.028289457},
{"learn":[632.7162533],"iteration":624,"passed_time":1.708553528,"remaining_time":1.025132117},
{"learn":[631.4072423],"iteration":625,"passed_time":1.710826073,"remaining_time":1.022122925},
{"learn":[629.9405174],"iteration":626,"passed_time":1.713458815,"remaining_time":1.019330364},
{"learn":[628.6551893],"iteration":627,"passed_time":1.715799228,"remaining_time":1.016365148},
{"learn":[627.7321575],"iteration":628,"passed_time":1.718276135,"remaining_time":1.013482426},
{"learn":[626.8914855],"iteration":629,"passed_time":1.720498367,"remaining_time":1.010451422},
{"learn":[625.5912545],"iteration":630,"passed_time":1.721770971,"remaining_time":1.006867652},
{"learn":[624.7508761],"iteration":631,"passed_time":1.723240027,"remaining_time":1.003405586},
{"learn":[624.2573028],"iteration":632,"passed_time":1.725415693,"remaining_time":1.000359494},
{"learn":[623.3023901],"iteration":633,"passed_time":1.728223231,"remaining_time":0.9976809187},
{"learn":[622.7306478],"iteration":634,"passed_time":1.72997846,"remaining_time":0.9943970676},
{"learn":[622.2068835],"iteration":635,"passed_time":1.732494093,"remaining_time":0.9915532232},
{"learn":[621.4235229],"iteration":636,"passed_time":1.734668898,"remaining_time":0.9885161852},
{"learn":[620.9994466],"iteration":637,"passed_time":1.736466118,"remaining_time":0.9852676095},
{"learn":[619.9735716],"iteration":638,"passed_time":1.739436449,"remaining_time":0.9826863194},
{"learn":[619.2195433],"iteration":639,"passed_time":1.742401667,"remaining_time":0.9801009375},
{"learn":[618.6528572],"iteration":640,"passed_time":1.745161989,"remaining_time":0.9773996165},
{"learn":[617.7110068],"iteration":641,"passed_time":1.747957018,"remaining_time":0.9747174647},
{"learn":[616.5984427],"iteration":642,"passed_time":1.750533914,"remaining_time":0.9719138526},
{"learn":[615.7210724],"iteration":643,"passed_time":1.752184359,"remaining_time":0.9685988069},
{"learn":[615.4478483],"iteration":644,"passed_time":1.753864266,"remaining_time":0.9653051388},
{"learn":[614.4744212],"iteration":645,"passed_time":1.756309128,"remaining_time":0.9624356523},
{"learn":[613.9564091],"iteration":646,"passed_time":1.759220348,"remaining_time":0.9598219208},
{"learn":[613.3432047],"iteration":647,"passed_time":1.761894566,"remaining_time":0.9570785296},
{"learn":[611.6813045],"iteration":648,"passed_time":1.764626146,"remaining_time":0.9543663748},
{"learn":[611.1965768],"iteration":649,"passed_time":1.767008988,"remaining_time":0.9514663781},
{"learn":[610.5626215],"iteration":650,"passed_time":1.768796207,"remaining_time":0.9482486579},
{"learn":[609.7167186],"iteration":651,"passed_time":1.770600008,"remaining_time":0.9450441761},
{"learn":[608.7880952],"iteration":652,"passed_time":1.773435204,"remaining_time":0.942392061},
{"learn":[607.4748736],"iteration":653,"passed_time":1.775644598,"remaining_time":0.9394083039},
{"learn":[606.4641539],"iteration":654,"passed_time":1.778554245,"remaining_time":0.9367957475},
{"learn":[605.8650031],"iteration":655,"passed_time":1.780931668,"remaining_time":0.9339031917},
{"learn":[604.731916],"iteration":656,"passed_time":1.782330771,"remaining_time":0.9305014528},
{"learn":[603.397478],"iteration":657,"passed_time":1.784059172,"remaining_time":0.9272769559},
{"learn":[602.6074566],"iteration":658,"passed_time":1.78615405,"remaining_time":0.9242466328},
{"learn":[601.8135652],"iteration":659,"passed_time":1.788804734,"remaining_time":0.9215054692},
{"learn":[601.1450194],"iteration":660,"passed_time":1.791466751,"remaining_time":0.9187703913},
{"learn":[599.7366554],"iteration":661,"passed_time":1.793828098,"remaining_time":0.9158820196},
{"learn":[599.1066571],"iteration":662,"passed_time":1.795701064,"remaining_time":0.9127469965},
{"learn":[598.8653874],"iteration":663,"passed_time":1.797172963,"remaining_time":0.9094128246},
{"learn":[598.6483582],"iteration":664,"passed_time":1.79888649,"remaining_time":0.9062059763},
{"learn":[597.357209],"iteration":665,"passed_time":1.800414036,"remaining_time":0.9029103423},
{"learn":[596.415759],"iteration":666,"passed_time":1.802500478,"remaining_time":0.8998990393},
{"learn":[595.9437563],"iteration":667,"passed_time":1.805276699,"remaining_time":0.8972333293},
{"learn":[595.1484608],"iteration":668,"passed_time":1.807871472,"remaining_time":0.8944775146},
{"learn":[594.4889217],"iteration":669,"passed_time":1.810744384,"remaining_time":0.8918591744},
{"learn":[593.8593904],"iteration":670,"passed_time":1.812623171,"remaining_time":0.8887526425},
{"learn":[593.2734356],"iteration":671,"passed_time":1.814606077,"remaining_time":0.8857005851},
{"learn":[592.4084086],"iteration":672,"passed_time":1.817079024,"remaining_time":0.8828898081},
{"learn":[591.8301105],"iteration":673,"passed_time":1.819876154,"remaining_time":0.8802368343},
{"learn":[591.2814233],"iteration":674,"passed_time":1.822561994,"remaining_time":0.8775298491},
{"learn":[590.0173992],"iteration":675,"passed_time":1.825296779,"remaining_time":0.8748463851},
{"learn":[588.9339369],"iteration":676,"passed_time":1.827435417,"remaining_time":0.871878345},
{"learn":[587.8076543],"iteration":677,"passed_time":1.829307099,"remaining_time":0.8687859674},
{"learn":[586.9488129],"iteration":678,"passed_time":1.830746257,"remaining_time":0.8654927077},
{"learn":[585.9374363],"iteration":679,"passed_time":1.833243799,"remaining_time":0.8627029643},
{"learn":[585.360834],"iteration":680,"passed_time":1.835592049,"remaining_time":0.8598441461},
{"learn":[584.7645847],"iteration":681,"passed_time":1.838145217,"remaining_time":0.857082374},
{"learn":[583.4994889],"iteration":682,"passed_time":1.840602258,"remaining_time":0.8542765972},
{"learn":[583.080035],"iteration":683,"passed_time":1.8421636,"remaining_time":0.8510580375},
{"learn":[582.1544681],"iteration":684,"passed_time":1.84359123,"remaining_time":0.8477828283},
{"learn":[581.6914996],"iteration":685,"passed_time":1.845265208,"remaining_time":0.8446257658},
{"learn":[580.5583703],"iteration":686,"passed_time":1.847332027,"remaining_time":0.8416520005},
{"learn":[579.368461],"iteration":687,"passed_time":1.849311665,"remaining_time":0.8386413366},
{"learn":[578.5085441],"iteration":688,"passed_time":1.851305413,"remaining_time":0.835640034},
{"learn":[577.5694011],"iteration":689,"passed_time":1.854086011,"remaining_time":0.8329951644},
{"learn":[576.579197],"iteration":690,"passed_time":1.856861723,"remaining_time":0.830347717},
{"learn":[576.0782252],"iteration":691,"passed_time":1.858418736,"remaining_time":0.8271574721},
{"learn":[575.4942344],"iteration":692,"passed_time":1.859959147,"remaining_time":0.8239645859},
{"learn":[574.5048484],"iteration":693,"passed_time":1.861300357,"remaining_time":0.82068863},
{"learn":[574.1193455],"iteration":694,"passed_time":1.863292304,"remaining_time":0.8177038171},
{"learn":[573.2767307],"iteration":695,"passed_time":1.865358954,"remaining_time":0.8147544857},
{"learn":[572.3671143],"iteration":696,"passed_time":1.86738867,"remaining_time":0.8117916315},
{"learn":[571.0713051],"iteration":697,"passed_time":1.869193568,"remaining_time":0.8087341799},
{"learn":[570.4952505],"iteration":698,"passed_time":1.871206679,"remaining_time":0.8057699721},
{"learn":[569.9470598],"iteration":699,"passed_time":1.872877628,"remaining_time":0.8026618406},
{"learn":[569.4278743],"iteration":700,"passed_time":1.874353285,"remaining_time":0.7994745109},
{"learn":[568.9463362],"iteration":701,"passed_time":1.876413225,"remaining_time":0.7965400868},
{"learn":[568.1437339],"iteration":702,"passed_time":1.879089614,"remaining_time":0.793868585},
{"learn":[567.5343087],"iteration":703,"passed_time":1.881841487,"remaining_time":0.7912288072},
{"learn":[566.4040694],"iteration":704,"passed_time":1.884264135,"remaining_time":0.7884509503},
{"learn":[566.1464721],"iteration":705,"passed_time":1.886685175,"remaining_time":0.7856734297},
{"learn":[565.2110517],"iteration":706,"passed_time":1.888643232,"remaining_time":0.7827050452},
{"learn":[564.7656834],"iteration":707,"passed_time":1.890282192,"remaining_time":0.7796079098},
{"learn":[564.0876187],"iteration":708,"passed_time":1.892091973,"remaining_time":0.7765849988},
{"learn":[563.7224161],"iteration":709,"passed_time":1.8947051,"remaining_time":0.7738936324},
{"learn":[563.3150045],"iteration":710,"passed_time":1.89706563,"remaining_time":0.771099813},
{"learn":[562.8876737],"iteration":711,"passed_time":1.899590568,"remaining_time":0.7683737127},
{"learn":[562.0993026],"iteration":712,"passed_time":1.901837094,"remaining_time":0.7655361093},
{"learn":[561.3975296],"iteration":713,"passed_time":1.903830396,"remaining_time":0.76259873},
{"learn":[561.011281],"iteration":714,"passed_time":1.906181686,"remaining_time":0.7598066859},
{"learn":[560.8640044],"iteration":715,"passed_time":1.907752073,"remaining_time":0.7567061293},
{"learn":[559.9498813],"iteration":716,"passed_time":1.909402396,"remaining_time":0.7536413921},
{"learn":[559.1066112],"iteration":717,"passed_time":1.911538748,"remaining_time":0.7507714858},
{"learn":[558.518217],"iteration":718,"passed_time":1.913267954,"remaining_time":0.7477444995},
{"learn":[558.3486529],"iteration":719,"passed_time":1.915207814,"remaining_time":0.744803039},
{"learn":[557.9523369],"iteration":720,"passed_time":1.917338268,"remaining_time":0.7419381094},
{"learn":[557.5773421],"iteration":721,"passed_time":1.919268079,"remaining_time":0.7389979583},
{"learn":[556.4079417],"iteration":722,"passed_time":1.920636297,"remaining_time":0.7358454416},
{"learn":[555.419439],"iteration":723,"passed_time":1.921788438,"remaining_time":0.7326154818},
{"learn":[554.8974809],"iteration":724,"passed_time":1.923792618,"remaining_time":0.7297144412},
{"learn":[554.7498323],"iteration":725,"passed_time":1.926590776,"remaining_time":0.7271155272},
{"learn":[553.7761975],"iteration":726,"passed_time":1.929300826,"remaining_time":0.7244829788},
{"learn":[552.9041448],"iteration":727,"passed_time":1.932069596,"remaining_time":0.7218721569},
{"learn":[552.1726988],"iteration":728,"passed_time":1.934260654,"remaining_time":0.7190461414},
{"learn":[552.0201979],"iteration":729,"passed_time":1.935700524,"remaining_time":0.7159440294},
{"learn":[551.2251736],"iteration":730,"passed_time":1.937396398,"remaining_time":0.7129406719},
{"learn":[550.8366665],"iteration":731,"passed_time":1.939574045,"remaining_time":0.7101172733},
{"learn":[549.8356906],"iteration":732,"passed_time":1.942327332,"remaining_time":0.7075053174},
{"learn":[548.9524572],"iteration":733,"passed_time":1.945087717,"remaining_time":0.7048955486},
{"learn":[548.0084593],"iteration":734,"passed_time":1.947808592,"remaining_time":0.7022711251},
{"learn":[547.5436521],"iteration":735,"passed_time":1.949715166,"remaining_time":0.6993543532},
{"learn":[547.0218241],"iteration":736,"passed_time":1.951341614,"remaining_time":0.6963403589},
{"learn":[546.5254329],"iteration":737,"passed_time":1.953078215,"remaining_time":0.6933692309},
{"learn":[546.4398191],"iteration":738,"passed_time":1.955696292,"remaining_time":0.6907127634},
{"learn":[546.1224902],"iteration":739,"passed_time":1.95838477,"remaining_time":0.6880811354},
{"learn":[545.9852925],"iteration":740,"passed_time":1.961255088,"remaining_time":0.685512912},
{"learn":[545.7487966],"iteration":741,"passed_time":1.9634409,"remaining_time":0.6827058654},
{"learn":[545.0666045],"iteration":742,"passed_time":1.964794636,"remaining_time":0.6796126801},
{"learn":[544.7382758],"iteration":743,"passed_time":1.966202785,"remaining_time":0.6765428938},
{"learn":[544.5711059],"iteration":744,"passed_time":1.968410445,"remaining_time":0.6737512261},
{"learn":[543.4719466],"iteration":745,"passed_time":1.970892515,"remaining_time":0.6710545562},
{"learn":[542.5329822],"iteration":746,"passed_time":1.973460052,"remaining_time":0.6683874073},
{"learn":[541.9088094],"iteration":747,"passed_time":1.975953324,"remaining_time":0.665695505},
{"learn":[541.5470642],"iteration":748,"passed_time":1.978726768,"remaining_time":0.6630980224},
{"learn":[540.7614021],"iteration":749,"passed_time":1.980288692,"remaining_time":0.6600962308},
{"learn":[540.3048544],"iteration":750,"passed_time":1.998052542,"remaining_time":0.6624701503},
{"learn":[539.9346102],"iteration":751,"passed_time":1.999758598,"remaining_time":0.6594948568},
{"learn":[539.6242668],"iteration":752,"passed_time":2.001751073,"remaining_time":0.6566168857},
{"learn":[539.0274062],"iteration":753,"passed_time":2.004128562,"remaining_time":0.6538668784},
{"learn":[538.1914944],"iteration":754,"passed_time":2.007107867,"remaining_time":0.651313149},
{"learn":[537.9384718],"iteration":755,"passed_time":2.010052031,"remaining_time":0.6487469518},
{"learn":[537.8702187],"iteration":756,"passed_time":2.012428181,"remaining_time":0.6459974215},
{"learn":[537.1048338],"iteration":757,"passed_time":2.014338741,"remaining_time":0.6431002313},
{"learn":[537.0242799],"iteration":758,"passed_time":2.016438576,"remaining_time":0.6402657401},
{"learn":[536.6087784],"iteration":759,"passed_time":2.019264498,"remaining_time":0.6376624729},
{"learn":[536.0339331],"iteration":760,"passed_time":2.021702692,"remaining_time":0.6349368508},
{"learn":[535.9283339],"iteration":761,"passed_time":2.024587738,"remaining_time":0.6323515506},
{"learn":[535.4019015],"iteration":762,"passed_time":2.026897875,"remaining_time":0.6295868891},
{"learn":[535.0327404],"iteration":763,"passed_time":2.028387248,"remaining_time":0.6265698828},
{"learn":[534.3564394],"iteration":764,"passed_time":2.030461165,"remaining_time":0.6237364364},
{"learn":[534.1720408],"iteration":765,"passed_time":2.033378023,"remaining_time":0.6211624769},
{"learn":[533.8605983],"iteration":766,"passed_time":2.035860473,"remaining_time":0.6184556586},
{"learn":[533.6407463],"iteration":767,"passed_time":2.038614627,"remaining_time":0.6158315018},
{"learn":[533.2354159],"iteration":768,"passed_time":2.04110625,"remaining_time":0.6131281454},
{"learn":[532.117278],"iteration":769,"passed_time":2.042387721,"remaining_time":0.6100638646},
{"learn":[531.9595552],"iteration":770,"passed_time":2.043719776,"remaining_time":0.607019233},
{"learn":[530.7736888],"iteration":771,"passed_time":2.045570611,"remaining_time":0.6041322529},
{"learn":[530.2757374],"iteration":772,"passed_time":2.048011269,"remaining_time":0.6014211619},
{"learn":[529.7937657],"iteration":773,"passed_time":2.050390532,"remaining_time":0.5986928427},
{"learn":[528.8245701],"iteration":774,"passed_time":2.053077654,"remaining_time":0.5960548028},
{"learn":[528.0767044],"iteration":775,"passed_time":2.055275438,"remaining_time":0.5932753842},
{"learn":[527.7699628],"iteration":776,"passed_time":2.056875253,"remaining_time":0.5903258449},
{"learn":[526.820115],"iteration":777,"passed_time":2.058352739,"remaining_time":0.5873448689},
{"learn":[526.2370162],"iteration":778,"passed_time":2.060358726,"remaining_time":0.5845176875},
{"learn":[526.1804087],"iteration":779,"passed_time":2.061336968,"remaining_time":0.5814027346},
{"learn":[525.2783014],"iteration":780,"passed_time":2.064136503,"remaining_time":0.5788039617},
{"learn":[524.939851],"iteration":781,"passed_time":2.066999717,"remaining_time":0.5762224276},
{"learn":[524.8815341],"iteration":782,"passed_time":2.069224147,"remaining_time":0.5734631415},
{"learn":[524.2511317],"iteration":783,"passed_time":2.071909893,"remaining_time":0.5708323175},
{"learn":[524.160941],"iteration":784,"passed_time":2.072780788,"remaining_time":0.5677042923},
{"learn":[523.862396],"iteration":785,"passed_time":2.074021536,"remaining_time":0.5646827082},
{"learn":[523.4469905],"iteration":786,"passed_time":2.075588859,"remaining_time":0.5617540369},
{"learn":[522.6086048],"iteration":787,"passed_time":2.078056504,"remaining_time":0.559071039},
{"learn":[521.5949688],"iteration":788,"passed_time":2.080749693,"remaining_time":0.5564489039},
{"learn":[520.7173996],"iteration":789,"passed_time":2.083256028,"remaining_time":0.5537769187},
{"learn":[519.7198096],"iteration":790,"passed_time":2.085623294,"remaining_time":0.5510686073},
{"learn":[519.5058512],"iteration":791,"passed_time":2.087957513,"remaining_time":0.548352478},
{"learn":[519.4417407],"iteration":792,"passed_time":2.089380032,"remaining_time":0.5453993273},
{"learn":[519.2251422],"iteration":793,"passed_time":2.091184189,"remaining_time":0.5425490465},
{"learn":[518.7628157],"iteration":794,"passed_time":2.093831052,"remaining_time":0.5399186989},
{"learn":[518.1585911],"iteration":795,"passed_time":2.096594263,"remaining_time":0.5373181277},
{"learn":[517.6161751],"iteration":796,"passed_time":2.099295117,"remaining_time":0.5347012656},
{"learn":[517.1824537],"iteration":797,"passed_time":2.102108363,"remaining_time":0.5321126431},
{"learn":[516.6926175],"iteration":798,"passed_time":2.105008779,"remaining_time":0.5295453876},
{"learn":[516.4497451],"iteration":799,"passed_time":2.107956079,"remaining_time":0.5269890197},
{"learn":[515.7139651],"iteration":800,"passed_time":2.110548767,"remaining_time":0.5243435764},
{"learn":[515.5700145],"iteration":801,"passed_time":2.113289356,"remaining_time":0.5217347786},
{"learn":[515.0982189],"iteration":802,"passed_time":2.116021575,"remaining_time":0.5191235995},
{"learn":[514.7007057],"iteration":803,"passed_time":2.118635675,"remaining_time":0.5164833237},
{"learn":[514.4288485],"iteration":804,"passed_time":2.120636013,"remaining_time":0.513694438},
{"learn":[514.1218265],"iteration":805,"passed_time":2.122412516,"remaining_time":0.5108536328},
{"learn":[513.8345077],"iteration":806,"passed_time":2.124614343,"remaining_time":0.508117185},
{"learn":[513.3670075],"iteration":807,"passed_time":2.127325587,"remaining_time":0.5055031098},
{"learn":[513.2709192],"iteration":808,"passed_time":2.12917978,"remaining_time":0.5026864498},
{"learn":[512.8227602],"iteration":809,"passed_time":2.131981275,"remaining_time":0.5000943732},
{"learn":[512.1327044],"iteration":810,"passed_time":2.134466388,"remaining_time":0.4974280484},
{"learn":[511.9346589],"iteration":811,"passed_time":2.136455998,"remaining_time":0.4946474478},
{"learn":[511.1655961],"iteration":812,"passed_time":2.139059644,"remaining_time":0.4920100288},
{"learn":[510.4287081],"iteration":813,"passed_time":2.142032037,"remaining_time":0.4894569519},
{"learn":[509.5321459],"iteration":814,"passed_time":2.144621986,"remaining_time":0.4868160336},
{"learn":[509.1884401],"iteration":815,"passed_time":2.147279501,"remaining_time":0.4841904758},
{"learn":[508.5416379],"iteration":816,"passed_time":2.149722457,"remaining_time":0.4815167805},
{"learn":[507.9914467],"iteration":817,"passed_time":2.151012304,"remaining_time":0.4785870896},
{"learn":[507.3428425],"iteration":818,"passed_time":2.15285783,"remaining_time":0.4757842091},
{"learn":[507.0085462],"iteration":819,"passed_time":2.155217362,"remaining_time":0.4730964941},
{"learn":[506.7367699],"iteration":820,"passed_time":2.158058096,"remaining_time":0.4705144935},
{"learn":[506.3951388],"iteration":821,"passed_time":2.160722157,"remaining_time":0.4678936059},
{"learn":[505.6432541],"iteration":822,"passed_time":2.163335612,"remaining_time":0.4652617295},
{"learn":[505.3647595],"iteration":823,"passed_time":2.164917138,"remaining_time":0.4624094858},
{"learn":[505.2085116],"iteration":824,"passed_time":2.166484152,"remaining_time":0.4595572444},
{"learn":[505.0583199],"iteration":825,"passed_time":2.168539926,"remaining_time":0.4568110741},
{"learn":[504.2469504],"iteration":826,"passed_time":2.171355716,"remaining_time":0.454225561},
{"learn":[503.9928528],"iteration":827,"passed_time":2.174165788,"remaining_time":0.4516383039},
{"learn":[503.3695442],"iteration":828,"passed_time":2.176874443,"remaining_time":0.4490295896},
{"learn":[503.0600972],"iteration":829,"passed_time":2.179509065,"remaining_time":0.4464054711},
{"learn":[502.7105129],"iteration":830,"passed_time":2.18133433,"remaining_time":0.443616729},
{"learn":[502.0036963],"iteration":831,"passed_time":2.183124372,"remaining_time":0.4408231905},
{"learn":[501.2962625],"iteration":832,"passed_time":2.185666359,"remaining_time":0.4381828114},
{"learn":[500.7881978],"iteration":833,"passed_time":2.188488611,"remaining_time":0.4355984526},
{"learn":[500.3256733],"iteration":834,"passed_time":2.191074167,"remaining_time":0.4329667516},
{"learn":[499.9931585],"iteration":835,"passed_time":2.193972318,"remaining_time":0.4303964834},
{"learn":[499.9449222],"iteration":836,"passed_time":2.196224806,"remaining_time":0.4276996934},
{"learn":[499.302444],"iteration":837,"passed_time":2.197939836,"remaining_time":0.4249000638},
{"learn":[498.4320301],"iteration":838,"passed_time":2.199697497,"remaining_time":0.4221112003},
{"learn":[498.3413459],"iteration":839,"passed_time":2.201217102,"remaining_time":0.4192794481},
{"learn":[498.295659],"iteration":840,"passed_time":2.20410239,"remaining_time":0.4167090131},
{"learn":[497.8713026],"iteration":841,"passed_time":2.207010831,"remaining_time":0.414142175},
{"learn":[497.6701708],"iteration":842,"passed_time":2.209875038,"remaining_time":0.4115662882},
{"learn":[496.8839923],"iteration":843,"passed_time":2.211564653,"remaining_time":0.4087726136},
{"learn":[496.1291907],"iteration":844,"passed_time":2.213438339,"remaining_time":0.4060153166},
{"learn":[495.6849231],"iteration":845,"passed_time":2.215497792,"remaining_time":0.4032939242},
{"learn":[495.4970539],"iteration":846,"passed_time":2.218092385,"remaining_time":0.4006707613},
{"learn":[495.2234201],"iteration":847,"passed_time":2.220593493,"remaining_time":0.3980309091},
{"learn":[495.1732606],"iteration":848,"passed_time":2.223230504,"remaining_time":0.3954155549},
{"learn":[494.2868073],"iteration":849,"passed_time":2.226111517,"remaining_time":0.3928432088},
{"learn":[493.6882941],"iteration":850,"passed_time":2.227714691,"remaining_time":0.3900464031},
{"learn":[493.5472611],"iteration":851,"passed_time":2.229802024,"remaining_time":0.3873365018},
{"learn":[493.2309406],"iteration":852,"passed_time":2.232374749,"remaining_time":0.3847117094},
{"learn":[492.8244224],"iteration":853,"passed_time":2.235323212,"remaining_time":0.3821512751},
{"learn":[492.617452],"iteration":854,"passed_time":2.237973445,"remaining_time":0.3795393562},
{"learn":[492.5793953],"iteration":855,"passed_time":2.240871855,"remaining_time":0.3769690971},
{"learn":[491.7171388],"iteration":856,"passed_time":2.242581387,"remaining_time":0.3741996948},
{"learn":[491.0651593],"iteration":857,"passed_time":2.244165479,"remaining_time":0.3714120024},
{"learn":[490.4878027],"iteration":858,"passed_time":2.246614868,"remaining_time":0.3687691459},
{"learn":[489.9745714],"iteration":859,"passed_time":2.248293189,"remaining_time":0.3660012168},
{"learn":[489.6697609],"iteration":860,"passed_time":2.251006549,"remaining_time":0.3634029155},
{"learn":[488.8669701],"iteration":861,"passed_time":2.25363164,"remaining_time":0.3607902162},
{"learn":[488.5111624],"iteration":862,"passed_time":2.256375721,"remaining_time":0.3581963775},
{"learn":[488.0248655],"iteration":863,"passed_time":2.258250526,"remaining_time":0.3554653605},
{"learn":[487.914956],"iteration":864,"passed_time":2.260284475,"remaining_time":0.3527611608},
{"learn":[487.8278581],"iteration":865,"passed_time":2.262982556,"remaining_time":0.3501612731},
{"learn":[487.6431614],"iteration":866,"passed_time":2.265832442,"remaining_time":0.3475844461},
{"learn":[487.1052491],"iteration":867,"passed_time":2.26795841,"remaining_time":0.344896901},
{"learn":[486.5793559],"iteration":868,"passed_time":2.270988449,"remaining_time":0.3423469354},
{"learn":[486.3981993],"iteration":869,"passed_time":2.272888212,"remaining_time":0.3396269742},
{"learn":[485.7139065],"iteration":870,"passed_time":2.274625846,"remaining_time":0.3368848842},
{"learn":[485.6715349],"iteration":871,"passed_time":2.277396761,"remaining_time":0.3342967722},
{"learn":[485.0131189],"iteration":872,"passed_time":2.279924935,"remaining_time":0.3316729287},
{"learn":[484.7702092],"iteration":873,"passed_time":2.282502021,"remaining_time":0.3290563554},
{"learn":[484.7330944],"iteration":874,"passed_time":2.285315386,"remaining_time":0.3264736266},
{"learn":[484.1509978],"iteration":875,"passed_time":2.287898579,"remaining_time":0.3238577898},
{"learn":[483.7836041],"iteration":876,"passed_time":2.290665136,"remaining_time":0.3212677442},
{"learn":[483.481789],"iteration":877,"passed_time":2.294071125,"remaining_time":0.3187661473},
{"learn":[483.4455356],"iteration":878,"passed_time":2.297320458,"remaining_time":0.3162409276},
{"learn":[483.2055876],"iteration":879,"passed_time":2.298930971,"remaining_time":0.3134905869},
{"learn":[483.1406395],"iteration":880,"passed_time":2.300321393,"remaining_time":0.3107131053},
{"learn":[482.7156333],"iteration":881,"passed_time":2.302685204,"remaining_time":0.3080689956},
{"learn":[482.3855378],"iteration":882,"passed_time":2.304356949,"remaining_time":0.3053338199},
{"learn":[481.805668],"iteration":883,"passed_time":2.305945456,"remaining_time":0.3025901276},
{"learn":[481.6949233],"iteration":884,"passed_time":2.308095544,"remaining_time":0.2999220199},
{"learn":[481.5985312],"iteration":885,"passed_time":2.310336499,"remaining_time":0.2972667731},
{"learn":[481.5016978],"iteration":886,"passed_time":2.311457546,"remaining_time":0.2944697888},
{"learn":[480.770081],"iteration":887,"passed_time":2.31407626,"remaining_time":0.2918654743},
{"learn":[480.588964],"iteration":888,"passed_time":2.317358971,"remaining_time":0.2893440335},
{"learn":[480.1004837],"iteration":889,"passed_time":2.318886177,"remaining_time":0.2866039095},
{"learn":[479.7021151],"iteration":890,"passed_time":2.32050744,"remaining_time":0.2838780146},
{"learn":[479.4476326],"iteration":891,"passed_time":2.323082714,"remaining_time":0.2812701044},
{"learn":[478.9190071],"iteration":892,"passed_time":2.325270889,"remaining_time":0.2786158847},
{"learn":[478.4360662],"iteration":893,"passed_time":2.328084693,"remaining_time":0.2760368875},
{"learn":[478.4002475],"iteration":894,"passed_time":2.33034341,"remaining_time":0.2733922437},
{"learn":[478.2248351],"iteration":895,"passed_time":2.332605236,"remaining_time":0.270748822},
{"learn":[477.7897867],"iteration":896,"passed_time":2.334606446,"remaining_time":0.2680763255},
{"learn":[477.7009703],"iteration":897,"passed_time":2.336212742,"remaining_time":0.2653604674},
{"learn":[477.1263038],"iteration":898,"passed_time":2.338892089,"remaining_time":0.2627676318},
{"learn":[476.81922],"iteration":899,"passed_time":2.341738514,"remaining_time":0.2601931682},
{"learn":[476.5826852],"iteration":900,"passed_time":2.343588544,"remaining_time":0.2575086191},
{"learn":[476.0192241],"iteration":901,"passed_time":2.34649459,"remaining_time":0.2549406539},
{"learn":[475.7470645],"iteration":902,"passed_time":2.349340223,"remaining_time":0.2523654503},
{"learn":[475.2625906],"iteration":903,"passed_time":2.351392554,"remaining_time":0.249705404},
{"learn":[475.226808],"iteration":904,"passed_time":2.354188523,"remaining_time":0.2471247621},
{"learn":[474.5792489],"iteration":905,"passed_time":2.356198341,"remaining_time":0.2444620795},
{"learn":[474.5419923],"iteration":906,"passed_time":2.35889312,"remaining_time":0.2418710696},
{"learn":[474.5025078],"iteration":907,"passed_time":2.361762004,"remaining_time":0.2392974718},
{"learn":[473.5919075],"iteration":908,"passed_time":2.363922714,"remaining_time":0.2366523289},
{"learn":[473.0144422],"iteration":909,"passed_time":2.365673351,"remaining_time":0.233967694},
{"learn":[472.9687006],"iteration":910,"passed_time":2.36838356,"remaining_time":0.2313788549},
{"learn":[472.1856435],"iteration":911,"passed_time":2.371134767,"remaining_time":0.2287937056},
{"learn":[471.8637911],"iteration":912,"passed_time":2.373982051,"remaining_time":0.2262173477},
{"learn":[471.344163],"iteration":913,"passed_time":2.376114834,"remaining_time":0.2235731682},
{"learn":[471.3127301],"iteration":914,"passed_time":2.379087983,"remaining_time":0.2210081733},
{"learn":[470.8116592],"iteration":915,"passed_time":2.380988836,"remaining_time":0.2183439544},
{"learn":[470.2275497],"iteration":916,"passed_time":2.383383943,"remaining_time":0.2157261366},
{"learn":[469.6491035],"iteration":917,"passed_time":2.386164556,"remaining_time":0.2131432392},
{"learn":[469.101423],"iteration":918,"passed_time":2.388462397,"remaining_time":0.2105173603},
{"learn":[468.8559257],"iteration":919,"passed_time":2.391086896,"remaining_time":0.2079205996},
{"learn":[468.8087511],"iteration":920,"passed_time":2.394269383,"remaining_time":0.2053716409},
{"learn":[468.5468423],"iteration":921,"passed_time":2.395602534,"remaining_time":0.2026648565},
{"learn":[468.3314178],"iteration":922,"passed_time":2.397244922,"remaining_time":0.1999868462},
{"learn":[467.999587],"iteration":923,"passed_time":2.400000741,"remaining_time":0.1974026583},
{"learn":[467.8625022],"iteration":924,"passed_time":2.401649612,"remaining_time":0.1947283469},
{"learn":[467.7053057],"iteration":925,"passed_time":2.404058916,"remaining_time":0.1921170192},
{"learn":[467.463766],"iteration":926,"passed_time":2.406804746,"remaining_time":0.1895326283},
{"learn":[466.9572608],"iteration":927,"passed_time":2.408423469,"remaining_time":0.1868604415},
{"learn":[466.4078605],"iteration":928,"passed_time":2.410870206,"remaining_time":0.1842538047},
{"learn":[465.8735612],"iteration":929,"passed_time":2.41234566,"remaining_time":0.1815744045},
{"learn":[465.1202278],"iteration":930,"passed_time":2.4145122,"remaining_time":0.1789488097},
{"learn":[464.6761549],"iteration":931,"passed_time":2.417341687,"remaining_time":0.1763725695},
{"learn":[464.0095069],"iteration":932,"passed_time":2.420157363,"remaining_time":0.1737947945},
{"learn":[463.9242446],"iteration":933,"passed_time":2.422075958,"remaining_time":0.1711531191},
{"learn":[463.4377939],"iteration":934,"passed_time":2.424790289,"remaining_time":0.1685683088},
{"learn":[463.2425183],"iteration":935,"passed_time":2.426789162,"remaining_time":0.1659343017},
{"learn":[463.0013877],"iteration":936,"passed_time":2.428846711,"remaining_time":0.1633055953},
{"learn":[462.4738563],"iteration":937,"passed_time":2.431813352,"remaining_time":0.160738196},
{"learn":[462.3349432],"iteration":938,"passed_time":2.434488461,"remaining_time":0.1581510076},
{"learn":[462.1937198],"iteration":939,"passed_time":2.437343398,"remaining_time":0.1555751105},
{"learn":[461.9053957],"iteration":940,"passed_time":2.44009806,"remaining_time":0.1529923332},
{"learn":[461.5038905],"iteration":941,"passed_time":2.442033923,"remaining_time":0.1503587766},
{"learn":[461.3639577],"iteration":942,"passed_time":2.444650811,"remaining_time":0.1477678645},
{"learn":[460.8698394],"iteration":943,"passed_time":2.446641843,"remaining_time":0.1451397703},
{"learn":[460.2799905],"iteration":944,"passed_time":2.449587977,"remaining_time":0.1425686124},
{"learn":[459.9309347],"iteration":945,"passed_time":2.452621641,"remaining_time":0.1400016582},
{"learn":[459.732209],"iteration":946,"passed_time":2.455067267,"remaining_time":0.137400808},
{"learn":[459.2515476],"iteration":947,"passed_time":2.457203458,"remaining_time":0.134783312},
{"learn":[458.8733157],"iteration":948,"passed_time":2.458674308,"remaining_time":0.1321310745},
{"learn":[458.4918529],"iteration":949,"passed_time":2.46005264,"remaining_time":0.1294764547},
{"learn":[458.4392789],"iteration":950,"passed_time":2.462367391,"remaining_time":0.1268727678},
{"learn":[458.3987109],"iteration":951,"passed_time":2.464230995,"remaining_time":0.1242469409},
{"learn":[457.9273614],"iteration":952,"passed_time":2.466748751,"remaining_time":0.1216549751},
{"learn":[457.4916922],"iteration":953,"passed_time":2.470026004,"remaining_time":0.1190997863},
{"learn":[457.2311463],"iteration":954,"passed_time":2.472919115,"remaining_time":0.1165249845},
{"learn":[456.8624173],"iteration":955,"passed_time":2.474793251,"remaining_time":0.1139026183},
{"learn":[456.6246088],"iteration":956,"passed_time":2.477449106,"remaining_time":0.11131694},
{"learn":[456.338629],"iteration":957,"passed_time":2.48009429,"remaining_time":0.1087306474},
{"learn":[456.0238838],"iteration":958,"passed_time":2.483787453,"remaining_time":0.106189036},
{"learn":[455.9413073],"iteration":959,"passed_time":2.486630839,"remaining_time":0.1036096183},
{"learn":[455.2377765],"iteration":960,"passed_time":2.488456931,"remaining_time":0.1009883666},
{"learn":[455.0555699],"iteration":961,"passed_time":2.490111177,"remaining_time":0.09836197995},
{"learn":[455.0223852],"iteration":962,"passed_time":2.492283252,"remaining_time":0.09575750813},
{"learn":[454.8268497],"iteration":963,"passed_time":2.493897204,"remaining_time":0.09313309062},
{"learn":[454.7521558],"iteration":964,"passed_time":2.495130362,"remaining_time":0.09049695615},
{"learn":[454.2641868],"iteration":965,"passed_time":2.497904731,"remaining_time":0.0879179719},
{"learn":[453.8028098],"iteration":966,"passed_time":2.50036796,"remaining_time":0.08532796553},
{"learn":[453.7189443],"iteration":967,"passed_time":2.50177634,"remaining_time":0.0827033501},
{"learn":[453.5851797],"iteration":968,"passed_time":2.503440721,"remaining_time":0.08008943484},
{"learn":[453.1496232],"iteration":969,"passed_time":2.505679731,"remaining_time":0.07749524941},
{"learn":[453.0178396],"iteration":970,"passed_time":2.50851914,"remaining_time":0.07491972716},
{"learn":[452.6232665],"iteration":971,"passed_time":2.511322159,"remaining_time":0.07234261364},
{"learn":[452.3995561],"iteration":972,"passed_time":2.514283652,"remaining_time":0.0697694333},
{"learn":[452.1921941],"iteration":973,"passed_time":2.517076671,"remaining_time":0.06719095838},
{"learn":[451.6051944],"iteration":974,"passed_time":2.519078247,"remaining_time":0.06459174992},
{"learn":[451.3921883],"iteration":975,"passed_time":2.521889258,"remaining_time":0.06201367028},
{"learn":[451.1537414],"iteration":976,"passed_time":2.524721294,"remaining_time":0.05943560875},
{"learn":[451.0392759],"iteration":977,"passed_time":2.527505089,"remaining_time":0.05685594271},
{"learn":[451.0083414],"iteration":978,"passed_time":2.528543936,"remaining_time":0.05423842968},
{"learn":[450.6971669],"iteration":979,"passed_time":2.531612453,"remaining_time":0.05166556026},
{"learn":[450.3580272],"iteration":980,"passed_time":2.534319449,"remaining_time":0.04908467842},
{"learn":[450.0101599],"iteration":981,"passed_time":2.537307155,"remaining_time":0.04650868512},
{"learn":[449.5867623],"iteration":982,"passed_time":2.540228566,"remaining_time":0.04393070766},
{"learn":[449.3823892],"iteration":983,"passed_time":2.543098581,"remaining_time":0.04135119644},
{"learn":[449.3425641],"iteration":984,"passed_time":2.544466756,"remaining_time":0.03874822471},
{"learn":[449.0615217],"iteration":985,"passed_time":2.547224625,"remaining_time":0.03616748961},
{"learn":[448.6794176],"iteration":986,"passed_time":2.54993097,"remaining_time":0.03358571693},
{"learn":[448.0712004],"iteration":987,"passed_time":2.552848436,"remaining_time":0.03100625631},
{"learn":[447.4750645],"iteration":988,"passed_time":2.555341194,"remaining_time":0.02842138841},
{"learn":[447.401647],"iteration":989,"passed_time":2.558162011,"remaining_time":0.02584002032},
{"learn":[446.8890584],"iteration":990,"passed_time":2.560803035,"remaining_time":0.02325653614},
{"learn":[446.2840506],"iteration":991,"passed_time":2.56358439,"remaining_time":0.02067406766},
{"learn":[445.7379219],"iteration":992,"passed_time":2.566414594,"remaining_time":0.01809154296},
{"learn":[445.6345366],"iteration":993,"passed_time":2.569143858,"remaining_time":0.01550791061},
{"learn":[445.5401332],"iteration":994,"passed_time":2.571780747,"remaining_time":0.01292352134},
{"learn":[445.1775599],"iteration":995,"passed_time":2.574197789,"remaining_time":0.01033814373},
{"learn":[444.8507714],"iteration":996,"passed_time":2.577829023,"remaining_time":0.007756757341},
{"learn":[444.3928814],"iteration":997,"passed_time":2.58067151,"remaining_time":0.005171686394},
{"learn":[444.1484297],"iteration":998,"passed_time":2.582597931,"remaining_time":0.002585183114},
{"learn":[443.8673362],"iteration":999,"passed_time":2.585212465,"remaining_time":0}
]}